  /*****************************************
  Emitting Generated Code
  *******************************************/
  class Generated(pConst_0:Object,pConst_1:Object,pConst_2:Object,pConst_3:Object,pConst_4:Object,pConst_5:Object,pConst_6:Object,pConst_7:Object) extends ((Int)=>(Int)) {
    def apply(x128:Int): Int = {
      val x0 = x128;
      val x7 = x0.asInstanceOf[Int];
      val x130: Int = {
        import sun.misc.Unsafe;
        val unsafe = { val fld = classOf[Unsafe].getDeclaredField("theUnsafe"); fld.setAccessible(true); fld.get(classOf[Unsafe]).asInstanceOf[Unsafe]; };
        type char = Char;
        def WARN = assert(false, "WARN");
        def ERROR = assert(false, "ERROR");
        var RES0 = null.asInstanceOf[Int];
        var vPHI_b9_2_5 = null.asInstanceOf[Int];
        // Sym(99);
        var vx7 = null.asInstanceOf[Int];
        // Sym(101);
        ;{;
          val PHI_b2_3_5 = 0 // LUBC(DynExp(PHI_b2_3_5):Int,Const(0):Int);
          BLOCK_2(PHI_b2_3_5,x7);
        };
        def BLOCK_2(PHI_b2_3_5:Int,x7:Int): Unit = {
          val x34 = x7 <= PHI_b2_3_5;
          val x42 = 50 != PHI_b2_3_5;
          val x68 = 1 + PHI_b2_3_5;
          if (x34) {
            val PHI_b9_2_5 = PHI_b2_3_5 // LUBC(Sym(56):Int,DynExp(PHI_b2_3_5):Int);
            vPHI_b9_2_5 = PHI_b9_2_5;
            vx7 = x7;
          } else {
            if (x42) {
              ;{;
                val PHI_b2_3_5 = x68 // LUBC(DynExp(PHI_b2_3_5):Int,Sym(68):Int);
                BLOCK_2(PHI_b2_3_5,x7);
              };
            } else {
              val x49: Object = pConst_0.asInstanceOf[lancet.api.DefaultMacrosLMS].mkInterpreterFrame(Array[Object](null.asInstanceOf[AnyRef],null.asInstanceOf[AnyRef],null.asInstanceOf[AnyRef],pConst_0.asInstanceOf[AnyRef],pConst_1.asInstanceOf[AnyRef],pConst_2.asInstanceOf[AnyRef],null.asInstanceOf[AnyRef],null.asInstanceOf[AnyRef],null.asInstanceOf[AnyRef],null.asInstanceOf[AnyRef],null.asInstanceOf[AnyRef],null.asInstanceOf[AnyRef]), -1,6,pConst_3.asInstanceOf[com.oracle.graal.api.meta.ResolvedJavaMethod],null);
              val x50: Object = pConst_0.asInstanceOf[lancet.api.DefaultMacrosLMS].mkInterpreterFrame(Array[Object](null.asInstanceOf[AnyRef],null.asInstanceOf[AnyRef],null.asInstanceOf[AnyRef],pConst_4.asInstanceOf[AnyRef],x7.asInstanceOf[AnyRef],null.asInstanceOf[AnyRef],null.asInstanceOf[AnyRef]), 5,5,pConst_1.asInstanceOf[com.oracle.graal.api.meta.ResolvedJavaMethod],x49);
              val x51: Object = pConst_0.asInstanceOf[lancet.api.DefaultMacrosLMS].mkInterpreterFrame(Array[Object](null.asInstanceOf[AnyRef],null.asInstanceOf[AnyRef],null.asInstanceOf[AnyRef],pConst_4.asInstanceOf[AnyRef],x7.asInstanceOf[AnyRef],PHI_b2_3_5.asInstanceOf[AnyRef],null.asInstanceOf[AnyRef],null.asInstanceOf[AnyRef],null.asInstanceOf[AnyRef]), 19,6,pConst_5.asInstanceOf[com.oracle.graal.api.meta.ResolvedJavaMethod],x50);
              val x52: Object = pConst_0.asInstanceOf[lancet.api.DefaultMacrosLMS].mkInterpreterFrame(Array[Object](null.asInstanceOf[AnyRef],null.asInstanceOf[AnyRef],null.asInstanceOf[AnyRef],pConst_6.asInstanceOf[AnyRef],PHI_b2_3_5.asInstanceOf[AnyRef],pConst_0.asInstanceOf[AnyRef],null.asInstanceOf[AnyRef],null.asInstanceOf[AnyRef]), 12,6,pConst_7.asInstanceOf[com.oracle.graal.api.meta.ResolvedJavaMethod],x51);
              val x53: Int = pConst_0.asInstanceOf[lancet.api.DefaultMacrosLMS].execInterpreter(x52).asInstanceOf[Int] // drop into interpreter;
              // old parent: 7:<TestInterpreter5$$anonfun$test1LMS$1.lancet$interpreter$TestInterpreter5$$anonfun$$compute$6>HotSpotSignature<(ILlancet/interpreter/TestInterpreter5$DecompilerLMS;)V> // 19:<TestInterpreter5$$anonfun$test1LMS$1$$anonfun$6.apply$mcII$sp>HotSpotSignature<(I)I> // 5:<TestInterpreter5$$anonfun$test1LMS$1$$anonfun$6.apply>HotSpotSignature<(I)I> // 0:<BytecodeInterpreter_Exec.execute>HotSpotSignature<(Ljava/lang/reflect/Method;[Ljava/lang/Object;)Ljava/lang/Object;>;
              // new parent: 5:<TestInterpreter5$$anonfun$test1LMS$1$$anonfun$6.apply>HotSpotSignature<(I)I> // 0:<BytecodeInterpreter_Exec.execute>HotSpotSignature<(Ljava/lang/reflect/Method;[Ljava/lang/Object;)Ljava/lang/Object;>;
              val x56 = x53.asInstanceOf[Int];
              val PHI_b9_2_5 = x56 // LUBC(DynExp(PHI_b2_3_5):Int,Sym(56):Int);
              vPHI_b9_2_5 = PHI_b9_2_5;
              vx7 = x7;
            }
            // WARNING: multiple returns (2) in HotSpotMethod<TestInterpreter5$$anonfun$test1LMS$1.lancet$interpreter$TestInterpreter5$$anonfun$$compute$6>;
          }
        }
        // WARNING: multiple returns (2) in HotSpotMethod<TestInterpreter5$$anonfun$test1LMS$1$$anonfun$6.apply$mcII$sp>;
        ;{;
          ;{;
            val PHI_b9_2_5 = vPHI_b9_2_5;
            val x7 = vx7;
            (RES0 = PHI_b9_2_5) // return to root;
          };
        };
        // (no return?);
        RES0
      };
      x130
    }
  }
  /*****************************************
  End of Generated Code
  *******************************************/
Vector((Sym(-1000),lancet.interpreter.TestInterpreter5$DecompilerLMS@40dfc732), (Sym(-1001),HotSpotMethod<TestInterpreter5$$anonfun$test1LMS$1$$anonfun$6.apply>), (Sym(-1002),[Lscala.virtualization.lms.internal.Expressions$Exp;@71f42120), (Sym(-1003),HotSpotMethod<BytecodeInterpreter_Exec.execute>), (Sym(-1004),<function1>), (Sym(-1005),HotSpotMethod<TestInterpreter5$$anonfun$test1LMS$1$$anonfun$6.apply$mcII$sp>), (Sym(-1006),<function0>), (Sym(-1007),HotSpotMethod<TestInterpreter5$$anonfun$test1LMS$1.lancet$interpreter$TestInterpreter5$$anonfun$$compute$6>))
List((lancet.interpreter.TestInterpreter5$DecompilerLMS@40dfc732,class java.lang.Object), (HotSpotMethod<TestInterpreter5$$anonfun$test1LMS$1$$anonfun$6.apply>,class java.lang.Object), ([Lscala.virtualization.lms.internal.Expressions$Exp;@71f42120,class java.lang.Object), (HotSpotMethod<BytecodeInterpreter_Exec.execute>,class java.lang.Object), (<function1>,class java.lang.Object), (HotSpotMethod<TestInterpreter5$$anonfun$test1LMS$1$$anonfun$6.apply$mcII$sp>,class java.lang.Object), (<function0>,class java.lang.Object), (HotSpotMethod<TestInterpreter5$$anonfun$test1LMS$1.lancet$interpreter$TestInterpreter5$$anonfun$$compute$6>,class java.lang.Object))
compilation: ok
-- start interpreting
frame:
HotSpotMethod<TestInterpreter5$$anonfun$test1LMS$1.lancet$interpreter$TestInterpreter5$$anonfun$$compute$6>
<function0>,50,lancet.interpreter.TestInterpreter5$DecompilerLMS@40dfc732,null,null
HotSpotMethod<TestInterpreter5$$anonfun$test1LMS$1$$anonfun$6.apply$mcII$sp>
<function1>,100,50,null,null,null
HotSpotMethod<TestInterpreter5$$anonfun$test1LMS$1$$anonfun$6.apply>
<function1>,100,null,null
HotSpotMethod<BytecodeInterpreter_Exec.execute>
lancet.interpreter.TestInterpreter5$DecompilerLMS@40dfc732,HotSpotMethod<TestInterpreter5$$anonfun$test1LMS$1$$anonfun$6.apply>,[Lscala.virtualization.lms.internal.Expressions$Exp;@71f42120,null,null,null,null,null,null
root:
HotSpotMethod<BytecodeInterpreter_Exec.execute>
lancet.interpreter.TestInterpreter5$DecompilerLMS@40dfc732,HotSpotMethod<TestInterpreter5$$anonfun$test1LMS$1$$anonfun$6.apply>,[Lscala.virtualization.lms.internal.Expressions$Exp;@71f42120,null,null,null,null,null,null
        RootCall HotSpotMethod<TestInterpreter5$$anonfun$test1LMS$1.lancet$interpreter$TestInterpreter5$$anonfun$$compute$6> - HotSpotSignature<(ILlancet/interpreter/TestInterpreter5$DecompilerLMS;)V>
        12: return
        Ret HotSpotMethod<TestInterpreter5$$anonfun$test1LMS$1.lancet$interpreter$TestInterpreter5$$anonfun$$compute$6> - HotSpotSignature<(ILlancet/interpreter/TestInterpreter5$DecompilerLMS;)V>
      19: iload_2
      20: iconst_1
      21: iadd
      22: istore_2
      23: getstatic
      26: pop
      27: goto
      2: iload_2
      3: iload_1
      4: if_icmpge
      7: aload_0
      8: getfield
      11: iload_2
      12: aload_0
      13: getfield
      16: invokevirtual
        Call HotSpotMethod<TestInterpreter5$$anonfun$test1LMS$1.lancet$interpreter$TestInterpreter5$$anonfun$$compute$6> - HotSpotSignature<(ILlancet/interpreter/TestInterpreter5$DecompilerLMS;)V>
        0: iload_1
        1: bipush
        3: if_icmpne
        12: return
        Ret HotSpotMethod<TestInterpreter5$$anonfun$test1LMS$1.lancet$interpreter$TestInterpreter5$$anonfun$$compute$6> - HotSpotSignature<(ILlancet/interpreter/TestInterpreter5$DecompilerLMS;)V>
      19: iload_2
      20: iconst_1
      21: iadd
      22: istore_2
      23: getstatic
      26: pop
      27: goto
      2: iload_2
      3: iload_1
      4: if_icmpge
      7: aload_0
      8: getfield
      11: iload_2
      12: aload_0
      13: getfield
      16: invokevirtual
        Call HotSpotMethod<TestInterpreter5$$anonfun$test1LMS$1.lancet$interpreter$TestInterpreter5$$anonfun$$compute$6> - HotSpotSignature<(ILlancet/interpreter/TestInterpreter5$DecompilerLMS;)V>
        0: iload_1
        1: bipush
        3: if_icmpne
        12: return
        Ret HotSpotMethod<TestInterpreter5$$anonfun$test1LMS$1.lancet$interpreter$TestInterpreter5$$anonfun$$compute$6> - HotSpotSignature<(ILlancet/interpreter/TestInterpreter5$DecompilerLMS;)V>
      19: iload_2
      20: iconst_1
      21: iadd
      22: istore_2
      23: getstatic
      26: pop
      27: goto
      2: iload_2
      3: iload_1
      4: if_icmpge
      7: aload_0
      8: getfield
      11: iload_2
      12: aload_0
      13: getfield
      16: invokevirtual
        Call HotSpotMethod<TestInterpreter5$$anonfun$test1LMS$1.lancet$interpreter$TestInterpreter5$$anonfun$$compute$6> - HotSpotSignature<(ILlancet/interpreter/TestInterpreter5$DecompilerLMS;)V>
        0: iload_1
        1: bipush
        3: if_icmpne
        12: return
        Ret HotSpotMethod<TestInterpreter5$$anonfun$test1LMS$1.lancet$interpreter$TestInterpreter5$$anonfun$$compute$6> - HotSpotSignature<(ILlancet/interpreter/TestInterpreter5$DecompilerLMS;)V>
      19: iload_2
      20: iconst_1
      21: iadd
      22: istore_2
      23: getstatic
      26: pop
      27: goto
      2: iload_2
      3: iload_1
      4: if_icmpge
      7: aload_0
      8: getfield
      11: iload_2
      12: aload_0
      13: getfield
      16: invokevirtual
        Call HotSpotMethod<TestInterpreter5$$anonfun$test1LMS$1.lancet$interpreter$TestInterpreter5$$anonfun$$compute$6> - HotSpotSignature<(ILlancet/interpreter/TestInterpreter5$DecompilerLMS;)V>
        0: iload_1
        1: bipush
        3: if_icmpne
        12: return
        Ret HotSpotMethod<TestInterpreter5$$anonfun$test1LMS$1.lancet$interpreter$TestInterpreter5$$anonfun$$compute$6> - HotSpotSignature<(ILlancet/interpreter/TestInterpreter5$DecompilerLMS;)V>
      19: iload_2
      20: iconst_1
      21: iadd
      22: istore_2
      23: getstatic
      26: pop
      27: goto
      2: iload_2
      3: iload_1
      4: if_icmpge
      7: aload_0
      8: getfield
      11: iload_2
      12: aload_0
      13: getfield
      16: invokevirtual
        Call HotSpotMethod<TestInterpreter5$$anonfun$test1LMS$1.lancet$interpreter$TestInterpreter5$$anonfun$$compute$6> - HotSpotSignature<(ILlancet/interpreter/TestInterpreter5$DecompilerLMS;)V>
        0: iload_1
        1: bipush
        3: if_icmpne
        12: return
        Ret HotSpotMethod<TestInterpreter5$$anonfun$test1LMS$1.lancet$interpreter$TestInterpreter5$$anonfun$$compute$6> - HotSpotSignature<(ILlancet/interpreter/TestInterpreter5$DecompilerLMS;)V>
      19: iload_2
      20: iconst_1
      21: iadd
      22: istore_2
      23: getstatic
      26: pop
      27: goto
      2: iload_2
      3: iload_1
      4: if_icmpge
      7: aload_0
      8: getfield
      11: iload_2
      12: aload_0
      13: getfield
      16: invokevirtual
        Call HotSpotMethod<TestInterpreter5$$anonfun$test1LMS$1.lancet$interpreter$TestInterpreter5$$anonfun$$compute$6> - HotSpotSignature<(ILlancet/interpreter/TestInterpreter5$DecompilerLMS;)V>
        0: iload_1
        1: bipush
        3: if_icmpne
        12: return
        Ret HotSpotMethod<TestInterpreter5$$anonfun$test1LMS$1.lancet$interpreter$TestInterpreter5$$anonfun$$compute$6> - HotSpotSignature<(ILlancet/interpreter/TestInterpreter5$DecompilerLMS;)V>
      19: iload_2
      20: iconst_1
      21: iadd
      22: istore_2
      23: getstatic
      26: pop
      27: goto
      2: iload_2
      3: iload_1
      4: if_icmpge
      7: aload_0
      8: getfield
      11: iload_2
      12: aload_0
      13: getfield
      16: invokevirtual
        Call HotSpotMethod<TestInterpreter5$$anonfun$test1LMS$1.lancet$interpreter$TestInterpreter5$$anonfun$$compute$6> - HotSpotSignature<(ILlancet/interpreter/TestInterpreter5$DecompilerLMS;)V>
        0: iload_1
        1: bipush
        3: if_icmpne
        12: return
        Ret HotSpotMethod<TestInterpreter5$$anonfun$test1LMS$1.lancet$interpreter$TestInterpreter5$$anonfun$$compute$6> - HotSpotSignature<(ILlancet/interpreter/TestInterpreter5$DecompilerLMS;)V>
      19: iload_2
      20: iconst_1
      21: iadd
      22: istore_2
      23: getstatic
      26: pop
      27: goto
      2: iload_2
      3: iload_1
      4: if_icmpge
      7: aload_0
      8: getfield
      11: iload_2
      12: aload_0
      13: getfield
      16: invokevirtual
        Call HotSpotMethod<TestInterpreter5$$anonfun$test1LMS$1.lancet$interpreter$TestInterpreter5$$anonfun$$compute$6> - HotSpotSignature<(ILlancet/interpreter/TestInterpreter5$DecompilerLMS;)V>
        0: iload_1
        1: bipush
        3: if_icmpne
        12: return
        Ret HotSpotMethod<TestInterpreter5$$anonfun$test1LMS$1.lancet$interpreter$TestInterpreter5$$anonfun$$compute$6> - HotSpotSignature<(ILlancet/interpreter/TestInterpreter5$DecompilerLMS;)V>
      19: iload_2
      20: iconst_1
      21: iadd
      22: istore_2
      23: getstatic
      26: pop
      27: goto
      2: iload_2
      3: iload_1
      4: if_icmpge
      7: aload_0
      8: getfield
      11: iload_2
      12: aload_0
      13: getfield
      16: invokevirtual
        Call HotSpotMethod<TestInterpreter5$$anonfun$test1LMS$1.lancet$interpreter$TestInterpreter5$$anonfun$$compute$6> - HotSpotSignature<(ILlancet/interpreter/TestInterpreter5$DecompilerLMS;)V>
        0: iload_1
        1: bipush
        3: if_icmpne
        12: return
        Ret HotSpotMethod<TestInterpreter5$$anonfun$test1LMS$1.lancet$interpreter$TestInterpreter5$$anonfun$$compute$6> - HotSpotSignature<(ILlancet/interpreter/TestInterpreter5$DecompilerLMS;)V>
      19: iload_2
      20: iconst_1
      21: iadd
      22: istore_2
      23: getstatic
      26: pop
      27: goto
      2: iload_2
      3: iload_1
      4: if_icmpge
      7: aload_0
      8: getfield
      11: iload_2
      12: aload_0
      13: getfield
      16: invokevirtual
        Call HotSpotMethod<TestInterpreter5$$anonfun$test1LMS$1.lancet$interpreter$TestInterpreter5$$anonfun$$compute$6> - HotSpotSignature<(ILlancet/interpreter/TestInterpreter5$DecompilerLMS;)V>
        0: iload_1
        1: bipush
        3: if_icmpne
        12: return
        Ret HotSpotMethod<TestInterpreter5$$anonfun$test1LMS$1.lancet$interpreter$TestInterpreter5$$anonfun$$compute$6> - HotSpotSignature<(ILlancet/interpreter/TestInterpreter5$DecompilerLMS;)V>
      19: iload_2
      20: iconst_1
      21: iadd
      22: istore_2
      23: getstatic
      26: pop
      27: goto
      2: iload_2
      3: iload_1
      4: if_icmpge
      7: aload_0
      8: getfield
      11: iload_2
      12: aload_0
      13: getfield
      16: invokevirtual
        Call HotSpotMethod<TestInterpreter5$$anonfun$test1LMS$1.lancet$interpreter$TestInterpreter5$$anonfun$$compute$6> - HotSpotSignature<(ILlancet/interpreter/TestInterpreter5$DecompilerLMS;)V>
        0: iload_1
        1: bipush
        3: if_icmpne
        12: return
        Ret HotSpotMethod<TestInterpreter5$$anonfun$test1LMS$1.lancet$interpreter$TestInterpreter5$$anonfun$$compute$6> - HotSpotSignature<(ILlancet/interpreter/TestInterpreter5$DecompilerLMS;)V>
      19: iload_2
      20: iconst_1
      21: iadd
      22: istore_2
      23: getstatic
      26: pop
      27: goto
      2: iload_2
      3: iload_1
      4: if_icmpge
      7: aload_0
      8: getfield
      11: iload_2
      12: aload_0
      13: getfield
      16: invokevirtual
        Call HotSpotMethod<TestInterpreter5$$anonfun$test1LMS$1.lancet$interpreter$TestInterpreter5$$anonfun$$compute$6> - HotSpotSignature<(ILlancet/interpreter/TestInterpreter5$DecompilerLMS;)V>
        0: iload_1
        1: bipush
        3: if_icmpne
        12: return
        Ret HotSpotMethod<TestInterpreter5$$anonfun$test1LMS$1.lancet$interpreter$TestInterpreter5$$anonfun$$compute$6> - HotSpotSignature<(ILlancet/interpreter/TestInterpreter5$DecompilerLMS;)V>
      19: iload_2
      20: iconst_1
      21: iadd
      22: istore_2
      23: getstatic
      26: pop
      27: goto
      2: iload_2
      3: iload_1
      4: if_icmpge
      7: aload_0
      8: getfield
      11: iload_2
      12: aload_0
      13: getfield
      16: invokevirtual
        Call HotSpotMethod<TestInterpreter5$$anonfun$test1LMS$1.lancet$interpreter$TestInterpreter5$$anonfun$$compute$6> - HotSpotSignature<(ILlancet/interpreter/TestInterpreter5$DecompilerLMS;)V>
        0: iload_1
        1: bipush
        3: if_icmpne
        12: return
        Ret HotSpotMethod<TestInterpreter5$$anonfun$test1LMS$1.lancet$interpreter$TestInterpreter5$$anonfun$$compute$6> - HotSpotSignature<(ILlancet/interpreter/TestInterpreter5$DecompilerLMS;)V>
      19: iload_2
      20: iconst_1
      21: iadd
      22: istore_2
      23: getstatic
      26: pop
      27: goto
      2: iload_2
      3: iload_1
      4: if_icmpge
      7: aload_0
      8: getfield
      11: iload_2
      12: aload_0
      13: getfield
      16: invokevirtual
        Call HotSpotMethod<TestInterpreter5$$anonfun$test1LMS$1.lancet$interpreter$TestInterpreter5$$anonfun$$compute$6> - HotSpotSignature<(ILlancet/interpreter/TestInterpreter5$DecompilerLMS;)V>
        0: iload_1
        1: bipush
        3: if_icmpne
        12: return
        Ret HotSpotMethod<TestInterpreter5$$anonfun$test1LMS$1.lancet$interpreter$TestInterpreter5$$anonfun$$compute$6> - HotSpotSignature<(ILlancet/interpreter/TestInterpreter5$DecompilerLMS;)V>
      19: iload_2
      20: iconst_1
      21: iadd
      22: istore_2
      23: getstatic
      26: pop
      27: goto
      2: iload_2
      3: iload_1
      4: if_icmpge
      7: aload_0
      8: getfield
      11: iload_2
      12: aload_0
      13: getfield
      16: invokevirtual
        Call HotSpotMethod<TestInterpreter5$$anonfun$test1LMS$1.lancet$interpreter$TestInterpreter5$$anonfun$$compute$6> - HotSpotSignature<(ILlancet/interpreter/TestInterpreter5$DecompilerLMS;)V>
        0: iload_1
        1: bipush
        3: if_icmpne
        12: return
        Ret HotSpotMethod<TestInterpreter5$$anonfun$test1LMS$1.lancet$interpreter$TestInterpreter5$$anonfun$$compute$6> - HotSpotSignature<(ILlancet/interpreter/TestInterpreter5$DecompilerLMS;)V>
      19: iload_2
      20: iconst_1
      21: iadd
      22: istore_2
      23: getstatic
      26: pop
      27: goto
      2: iload_2
      3: iload_1
      4: if_icmpge
      7: aload_0
      8: getfield
      11: iload_2
      12: aload_0
      13: getfield
      16: invokevirtual
        Call HotSpotMethod<TestInterpreter5$$anonfun$test1LMS$1.lancet$interpreter$TestInterpreter5$$anonfun$$compute$6> - HotSpotSignature<(ILlancet/interpreter/TestInterpreter5$DecompilerLMS;)V>
        0: iload_1
        1: bipush
        3: if_icmpne
        12: return
        Ret HotSpotMethod<TestInterpreter5$$anonfun$test1LMS$1.lancet$interpreter$TestInterpreter5$$anonfun$$compute$6> - HotSpotSignature<(ILlancet/interpreter/TestInterpreter5$DecompilerLMS;)V>
      19: iload_2
      20: iconst_1
      21: iadd
      22: istore_2
      23: getstatic
      26: pop
      27: goto
      2: iload_2
      3: iload_1
      4: if_icmpge
      7: aload_0
      8: getfield
      11: iload_2
      12: aload_0
      13: getfield
      16: invokevirtual
        Call HotSpotMethod<TestInterpreter5$$anonfun$test1LMS$1.lancet$interpreter$TestInterpreter5$$anonfun$$compute$6> - HotSpotSignature<(ILlancet/interpreter/TestInterpreter5$DecompilerLMS;)V>
        0: iload_1
        1: bipush
        3: if_icmpne
        12: return
        Ret HotSpotMethod<TestInterpreter5$$anonfun$test1LMS$1.lancet$interpreter$TestInterpreter5$$anonfun$$compute$6> - HotSpotSignature<(ILlancet/interpreter/TestInterpreter5$DecompilerLMS;)V>
      19: iload_2
      20: iconst_1
      21: iadd
      22: istore_2
      23: getstatic
      26: pop
      27: goto
      2: iload_2
      3: iload_1
      4: if_icmpge
      7: aload_0
      8: getfield
      11: iload_2
      12: aload_0
      13: getfield
      16: invokevirtual
        Call HotSpotMethod<TestInterpreter5$$anonfun$test1LMS$1.lancet$interpreter$TestInterpreter5$$anonfun$$compute$6> - HotSpotSignature<(ILlancet/interpreter/TestInterpreter5$DecompilerLMS;)V>
        0: iload_1
        1: bipush
        3: if_icmpne
        12: return
        Ret HotSpotMethod<TestInterpreter5$$anonfun$test1LMS$1.lancet$interpreter$TestInterpreter5$$anonfun$$compute$6> - HotSpotSignature<(ILlancet/interpreter/TestInterpreter5$DecompilerLMS;)V>
      19: iload_2
      20: iconst_1
      21: iadd
      22: istore_2
      23: getstatic
      26: pop
      27: goto
      2: iload_2
      3: iload_1
      4: if_icmpge
      7: aload_0
      8: getfield
      11: iload_2
      12: aload_0
      13: getfield
      16: invokevirtual
        Call HotSpotMethod<TestInterpreter5$$anonfun$test1LMS$1.lancet$interpreter$TestInterpreter5$$anonfun$$compute$6> - HotSpotSignature<(ILlancet/interpreter/TestInterpreter5$DecompilerLMS;)V>
        0: iload_1
        1: bipush
        3: if_icmpne
        12: return
        Ret HotSpotMethod<TestInterpreter5$$anonfun$test1LMS$1.lancet$interpreter$TestInterpreter5$$anonfun$$compute$6> - HotSpotSignature<(ILlancet/interpreter/TestInterpreter5$DecompilerLMS;)V>
      19: iload_2
      20: iconst_1
      21: iadd
      22: istore_2
      23: getstatic
      26: pop
      27: goto
      2: iload_2
      3: iload_1
      4: if_icmpge
      7: aload_0
      8: getfield
      11: iload_2
      12: aload_0
      13: getfield
      16: invokevirtual
        Call HotSpotMethod<TestInterpreter5$$anonfun$test1LMS$1.lancet$interpreter$TestInterpreter5$$anonfun$$compute$6> - HotSpotSignature<(ILlancet/interpreter/TestInterpreter5$DecompilerLMS;)V>
        0: iload_1
        1: bipush
        3: if_icmpne
        12: return
        Ret HotSpotMethod<TestInterpreter5$$anonfun$test1LMS$1.lancet$interpreter$TestInterpreter5$$anonfun$$compute$6> - HotSpotSignature<(ILlancet/interpreter/TestInterpreter5$DecompilerLMS;)V>
      19: iload_2
      20: iconst_1
      21: iadd
      22: istore_2
      23: getstatic
      26: pop
      27: goto
      2: iload_2
      3: iload_1
      4: if_icmpge
      7: aload_0
      8: getfield
      11: iload_2
      12: aload_0
      13: getfield
      16: invokevirtual
        Call HotSpotMethod<TestInterpreter5$$anonfun$test1LMS$1.lancet$interpreter$TestInterpreter5$$anonfun$$compute$6> - HotSpotSignature<(ILlancet/interpreter/TestInterpreter5$DecompilerLMS;)V>
        0: iload_1
        1: bipush
        3: if_icmpne
        12: return
        Ret HotSpotMethod<TestInterpreter5$$anonfun$test1LMS$1.lancet$interpreter$TestInterpreter5$$anonfun$$compute$6> - HotSpotSignature<(ILlancet/interpreter/TestInterpreter5$DecompilerLMS;)V>
      19: iload_2
      20: iconst_1
      21: iadd
      22: istore_2
      23: getstatic
      26: pop
      27: goto
      2: iload_2
      3: iload_1
      4: if_icmpge
      7: aload_0
      8: getfield
      11: iload_2
      12: aload_0
      13: getfield
      16: invokevirtual
        Call HotSpotMethod<TestInterpreter5$$anonfun$test1LMS$1.lancet$interpreter$TestInterpreter5$$anonfun$$compute$6> - HotSpotSignature<(ILlancet/interpreter/TestInterpreter5$DecompilerLMS;)V>
        0: iload_1
        1: bipush
        3: if_icmpne
        12: return
        Ret HotSpotMethod<TestInterpreter5$$anonfun$test1LMS$1.lancet$interpreter$TestInterpreter5$$anonfun$$compute$6> - HotSpotSignature<(ILlancet/interpreter/TestInterpreter5$DecompilerLMS;)V>
      19: iload_2
      20: iconst_1
      21: iadd
      22: istore_2
      23: getstatic
      26: pop
      27: goto
      2: iload_2
      3: iload_1
      4: if_icmpge
      7: aload_0
      8: getfield
      11: iload_2
      12: aload_0
      13: getfield
      16: invokevirtual
        Call HotSpotMethod<TestInterpreter5$$anonfun$test1LMS$1.lancet$interpreter$TestInterpreter5$$anonfun$$compute$6> - HotSpotSignature<(ILlancet/interpreter/TestInterpreter5$DecompilerLMS;)V>
        0: iload_1
        1: bipush
        3: if_icmpne
        12: return
        Ret HotSpotMethod<TestInterpreter5$$anonfun$test1LMS$1.lancet$interpreter$TestInterpreter5$$anonfun$$compute$6> - HotSpotSignature<(ILlancet/interpreter/TestInterpreter5$DecompilerLMS;)V>
      19: iload_2
      20: iconst_1
      21: iadd
      22: istore_2
      23: getstatic
      26: pop
      27: goto
      2: iload_2
      3: iload_1
      4: if_icmpge
      7: aload_0
      8: getfield
      11: iload_2
      12: aload_0
      13: getfield
      16: invokevirtual
        Call HotSpotMethod<TestInterpreter5$$anonfun$test1LMS$1.lancet$interpreter$TestInterpreter5$$anonfun$$compute$6> - HotSpotSignature<(ILlancet/interpreter/TestInterpreter5$DecompilerLMS;)V>
        0: iload_1
        1: bipush
        3: if_icmpne
        12: return
        Ret HotSpotMethod<TestInterpreter5$$anonfun$test1LMS$1.lancet$interpreter$TestInterpreter5$$anonfun$$compute$6> - HotSpotSignature<(ILlancet/interpreter/TestInterpreter5$DecompilerLMS;)V>
      19: iload_2
      20: iconst_1
      21: iadd
      22: istore_2
      23: getstatic
      26: pop
      27: goto
      2: iload_2
      3: iload_1
      4: if_icmpge
      7: aload_0
      8: getfield
      11: iload_2
      12: aload_0
      13: getfield
      16: invokevirtual
        Call HotSpotMethod<TestInterpreter5$$anonfun$test1LMS$1.lancet$interpreter$TestInterpreter5$$anonfun$$compute$6> - HotSpotSignature<(ILlancet/interpreter/TestInterpreter5$DecompilerLMS;)V>
        0: iload_1
        1: bipush
        3: if_icmpne
        12: return
        Ret HotSpotMethod<TestInterpreter5$$anonfun$test1LMS$1.lancet$interpreter$TestInterpreter5$$anonfun$$compute$6> - HotSpotSignature<(ILlancet/interpreter/TestInterpreter5$DecompilerLMS;)V>
      19: iload_2
      20: iconst_1
      21: iadd
      22: istore_2
      23: getstatic
      26: pop
      27: goto
      2: iload_2
      3: iload_1
      4: if_icmpge
      7: aload_0
      8: getfield
      11: iload_2
      12: aload_0
      13: getfield
      16: invokevirtual
        Call HotSpotMethod<TestInterpreter5$$anonfun$test1LMS$1.lancet$interpreter$TestInterpreter5$$anonfun$$compute$6> - HotSpotSignature<(ILlancet/interpreter/TestInterpreter5$DecompilerLMS;)V>
        0: iload_1
        1: bipush
        3: if_icmpne
        12: return
        Ret HotSpotMethod<TestInterpreter5$$anonfun$test1LMS$1.lancet$interpreter$TestInterpreter5$$anonfun$$compute$6> - HotSpotSignature<(ILlancet/interpreter/TestInterpreter5$DecompilerLMS;)V>
      19: iload_2
      20: iconst_1
      21: iadd
      22: istore_2
      23: getstatic
      26: pop
      27: goto
      2: iload_2
      3: iload_1
      4: if_icmpge
      7: aload_0
      8: getfield
      11: iload_2
      12: aload_0
      13: getfield
      16: invokevirtual
        Call HotSpotMethod<TestInterpreter5$$anonfun$test1LMS$1.lancet$interpreter$TestInterpreter5$$anonfun$$compute$6> - HotSpotSignature<(ILlancet/interpreter/TestInterpreter5$DecompilerLMS;)V>
        0: iload_1
        1: bipush
        3: if_icmpne
        12: return
        Ret HotSpotMethod<TestInterpreter5$$anonfun$test1LMS$1.lancet$interpreter$TestInterpreter5$$anonfun$$compute$6> - HotSpotSignature<(ILlancet/interpreter/TestInterpreter5$DecompilerLMS;)V>
      19: iload_2
      20: iconst_1
      21: iadd
      22: istore_2
      23: getstatic
      26: pop
      27: goto
      2: iload_2
      3: iload_1
      4: if_icmpge
      7: aload_0
      8: getfield
      11: iload_2
      12: aload_0
      13: getfield
      16: invokevirtual
        Call HotSpotMethod<TestInterpreter5$$anonfun$test1LMS$1.lancet$interpreter$TestInterpreter5$$anonfun$$compute$6> - HotSpotSignature<(ILlancet/interpreter/TestInterpreter5$DecompilerLMS;)V>
        0: iload_1
        1: bipush
        3: if_icmpne
        12: return
        Ret HotSpotMethod<TestInterpreter5$$anonfun$test1LMS$1.lancet$interpreter$TestInterpreter5$$anonfun$$compute$6> - HotSpotSignature<(ILlancet/interpreter/TestInterpreter5$DecompilerLMS;)V>
      19: iload_2
      20: iconst_1
      21: iadd
      22: istore_2
      23: getstatic
      26: pop
      27: goto
      2: iload_2
      3: iload_1
      4: if_icmpge
      7: aload_0
      8: getfield
      11: iload_2
      12: aload_0
      13: getfield
      16: invokevirtual
        Call HotSpotMethod<TestInterpreter5$$anonfun$test1LMS$1.lancet$interpreter$TestInterpreter5$$anonfun$$compute$6> - HotSpotSignature<(ILlancet/interpreter/TestInterpreter5$DecompilerLMS;)V>
        0: iload_1
        1: bipush
        3: if_icmpne
        12: return
        Ret HotSpotMethod<TestInterpreter5$$anonfun$test1LMS$1.lancet$interpreter$TestInterpreter5$$anonfun$$compute$6> - HotSpotSignature<(ILlancet/interpreter/TestInterpreter5$DecompilerLMS;)V>
      19: iload_2
      20: iconst_1
      21: iadd
      22: istore_2
      23: getstatic
      26: pop
      27: goto
      2: iload_2
      3: iload_1
      4: if_icmpge
      7: aload_0
      8: getfield
      11: iload_2
      12: aload_0
      13: getfield
      16: invokevirtual
        Call HotSpotMethod<TestInterpreter5$$anonfun$test1LMS$1.lancet$interpreter$TestInterpreter5$$anonfun$$compute$6> - HotSpotSignature<(ILlancet/interpreter/TestInterpreter5$DecompilerLMS;)V>
        0: iload_1
        1: bipush
        3: if_icmpne
        12: return
        Ret HotSpotMethod<TestInterpreter5$$anonfun$test1LMS$1.lancet$interpreter$TestInterpreter5$$anonfun$$compute$6> - HotSpotSignature<(ILlancet/interpreter/TestInterpreter5$DecompilerLMS;)V>
      19: iload_2
      20: iconst_1
      21: iadd
      22: istore_2
      23: getstatic
      26: pop
      27: goto
      2: iload_2
      3: iload_1
      4: if_icmpge
      7: aload_0
      8: getfield
      11: iload_2
      12: aload_0
      13: getfield
      16: invokevirtual
        Call HotSpotMethod<TestInterpreter5$$anonfun$test1LMS$1.lancet$interpreter$TestInterpreter5$$anonfun$$compute$6> - HotSpotSignature<(ILlancet/interpreter/TestInterpreter5$DecompilerLMS;)V>
        0: iload_1
        1: bipush
        3: if_icmpne
        12: return
        Ret HotSpotMethod<TestInterpreter5$$anonfun$test1LMS$1.lancet$interpreter$TestInterpreter5$$anonfun$$compute$6> - HotSpotSignature<(ILlancet/interpreter/TestInterpreter5$DecompilerLMS;)V>
      19: iload_2
      20: iconst_1
      21: iadd
      22: istore_2
      23: getstatic
      26: pop
      27: goto
      2: iload_2
      3: iload_1
      4: if_icmpge
      7: aload_0
      8: getfield
      11: iload_2
      12: aload_0
      13: getfield
      16: invokevirtual
        Call HotSpotMethod<TestInterpreter5$$anonfun$test1LMS$1.lancet$interpreter$TestInterpreter5$$anonfun$$compute$6> - HotSpotSignature<(ILlancet/interpreter/TestInterpreter5$DecompilerLMS;)V>
        0: iload_1
        1: bipush
        3: if_icmpne
        12: return
        Ret HotSpotMethod<TestInterpreter5$$anonfun$test1LMS$1.lancet$interpreter$TestInterpreter5$$anonfun$$compute$6> - HotSpotSignature<(ILlancet/interpreter/TestInterpreter5$DecompilerLMS;)V>
      19: iload_2
      20: iconst_1
      21: iadd
      22: istore_2
      23: getstatic
      26: pop
      27: goto
      2: iload_2
      3: iload_1
      4: if_icmpge
      7: aload_0
      8: getfield
      11: iload_2
      12: aload_0
      13: getfield
      16: invokevirtual
        Call HotSpotMethod<TestInterpreter5$$anonfun$test1LMS$1.lancet$interpreter$TestInterpreter5$$anonfun$$compute$6> - HotSpotSignature<(ILlancet/interpreter/TestInterpreter5$DecompilerLMS;)V>
        0: iload_1
        1: bipush
        3: if_icmpne
        12: return
        Ret HotSpotMethod<TestInterpreter5$$anonfun$test1LMS$1.lancet$interpreter$TestInterpreter5$$anonfun$$compute$6> - HotSpotSignature<(ILlancet/interpreter/TestInterpreter5$DecompilerLMS;)V>
      19: iload_2
      20: iconst_1
      21: iadd
      22: istore_2
      23: getstatic
      26: pop
      27: goto
      2: iload_2
      3: iload_1
      4: if_icmpge
      7: aload_0
      8: getfield
      11: iload_2
      12: aload_0
      13: getfield
      16: invokevirtual
        Call HotSpotMethod<TestInterpreter5$$anonfun$test1LMS$1.lancet$interpreter$TestInterpreter5$$anonfun$$compute$6> - HotSpotSignature<(ILlancet/interpreter/TestInterpreter5$DecompilerLMS;)V>
        0: iload_1
        1: bipush
        3: if_icmpne
        12: return
        Ret HotSpotMethod<TestInterpreter5$$anonfun$test1LMS$1.lancet$interpreter$TestInterpreter5$$anonfun$$compute$6> - HotSpotSignature<(ILlancet/interpreter/TestInterpreter5$DecompilerLMS;)V>
      19: iload_2
      20: iconst_1
      21: iadd
      22: istore_2
      23: getstatic
      26: pop
      27: goto
      2: iload_2
      3: iload_1
      4: if_icmpge
      7: aload_0
      8: getfield
      11: iload_2
      12: aload_0
      13: getfield
      16: invokevirtual
        Call HotSpotMethod<TestInterpreter5$$anonfun$test1LMS$1.lancet$interpreter$TestInterpreter5$$anonfun$$compute$6> - HotSpotSignature<(ILlancet/interpreter/TestInterpreter5$DecompilerLMS;)V>
        0: iload_1
        1: bipush
        3: if_icmpne
        12: return
        Ret HotSpotMethod<TestInterpreter5$$anonfun$test1LMS$1.lancet$interpreter$TestInterpreter5$$anonfun$$compute$6> - HotSpotSignature<(ILlancet/interpreter/TestInterpreter5$DecompilerLMS;)V>
      19: iload_2
      20: iconst_1
      21: iadd
      22: istore_2
      23: getstatic
      26: pop
      27: goto
      2: iload_2
      3: iload_1
      4: if_icmpge
      7: aload_0
      8: getfield
      11: iload_2
      12: aload_0
      13: getfield
      16: invokevirtual
        Call HotSpotMethod<TestInterpreter5$$anonfun$test1LMS$1.lancet$interpreter$TestInterpreter5$$anonfun$$compute$6> - HotSpotSignature<(ILlancet/interpreter/TestInterpreter5$DecompilerLMS;)V>
        0: iload_1
        1: bipush
        3: if_icmpne
        12: return
        Ret HotSpotMethod<TestInterpreter5$$anonfun$test1LMS$1.lancet$interpreter$TestInterpreter5$$anonfun$$compute$6> - HotSpotSignature<(ILlancet/interpreter/TestInterpreter5$DecompilerLMS;)V>
      19: iload_2
      20: iconst_1
      21: iadd
      22: istore_2
      23: getstatic
      26: pop
      27: goto
      2: iload_2
      3: iload_1
      4: if_icmpge
      7: aload_0
      8: getfield
      11: iload_2
      12: aload_0
      13: getfield
      16: invokevirtual
        Call HotSpotMethod<TestInterpreter5$$anonfun$test1LMS$1.lancet$interpreter$TestInterpreter5$$anonfun$$compute$6> - HotSpotSignature<(ILlancet/interpreter/TestInterpreter5$DecompilerLMS;)V>
        0: iload_1
        1: bipush
        3: if_icmpne
        12: return
        Ret HotSpotMethod<TestInterpreter5$$anonfun$test1LMS$1.lancet$interpreter$TestInterpreter5$$anonfun$$compute$6> - HotSpotSignature<(ILlancet/interpreter/TestInterpreter5$DecompilerLMS;)V>
      19: iload_2
      20: iconst_1
      21: iadd
      22: istore_2
      23: getstatic
      26: pop
      27: goto
      2: iload_2
      3: iload_1
      4: if_icmpge
      7: aload_0
      8: getfield
      11: iload_2
      12: aload_0
      13: getfield
      16: invokevirtual
        Call HotSpotMethod<TestInterpreter5$$anonfun$test1LMS$1.lancet$interpreter$TestInterpreter5$$anonfun$$compute$6> - HotSpotSignature<(ILlancet/interpreter/TestInterpreter5$DecompilerLMS;)V>
        0: iload_1
        1: bipush
        3: if_icmpne
        12: return
        Ret HotSpotMethod<TestInterpreter5$$anonfun$test1LMS$1.lancet$interpreter$TestInterpreter5$$anonfun$$compute$6> - HotSpotSignature<(ILlancet/interpreter/TestInterpreter5$DecompilerLMS;)V>
      19: iload_2
      20: iconst_1
      21: iadd
      22: istore_2
      23: getstatic
      26: pop
      27: goto
      2: iload_2
      3: iload_1
      4: if_icmpge
      7: aload_0
      8: getfield
      11: iload_2
      12: aload_0
      13: getfield
      16: invokevirtual
        Call HotSpotMethod<TestInterpreter5$$anonfun$test1LMS$1.lancet$interpreter$TestInterpreter5$$anonfun$$compute$6> - HotSpotSignature<(ILlancet/interpreter/TestInterpreter5$DecompilerLMS;)V>
        0: iload_1
        1: bipush
        3: if_icmpne
        12: return
        Ret HotSpotMethod<TestInterpreter5$$anonfun$test1LMS$1.lancet$interpreter$TestInterpreter5$$anonfun$$compute$6> - HotSpotSignature<(ILlancet/interpreter/TestInterpreter5$DecompilerLMS;)V>
      19: iload_2
      20: iconst_1
      21: iadd
      22: istore_2
      23: getstatic
      26: pop
      27: goto
      2: iload_2
      3: iload_1
      4: if_icmpge
      7: aload_0
      8: getfield
      11: iload_2
      12: aload_0
      13: getfield
      16: invokevirtual
        Call HotSpotMethod<TestInterpreter5$$anonfun$test1LMS$1.lancet$interpreter$TestInterpreter5$$anonfun$$compute$6> - HotSpotSignature<(ILlancet/interpreter/TestInterpreter5$DecompilerLMS;)V>
        0: iload_1
        1: bipush
        3: if_icmpne
        12: return
        Ret HotSpotMethod<TestInterpreter5$$anonfun$test1LMS$1.lancet$interpreter$TestInterpreter5$$anonfun$$compute$6> - HotSpotSignature<(ILlancet/interpreter/TestInterpreter5$DecompilerLMS;)V>
      19: iload_2
      20: iconst_1
      21: iadd
      22: istore_2
      23: getstatic
      26: pop
      27: goto
      2: iload_2
      3: iload_1
      4: if_icmpge
      7: aload_0
      8: getfield
      11: iload_2
      12: aload_0
      13: getfield
      16: invokevirtual
        Call HotSpotMethod<TestInterpreter5$$anonfun$test1LMS$1.lancet$interpreter$TestInterpreter5$$anonfun$$compute$6> - HotSpotSignature<(ILlancet/interpreter/TestInterpreter5$DecompilerLMS;)V>
        0: iload_1
        1: bipush
        3: if_icmpne
        12: return
        Ret HotSpotMethod<TestInterpreter5$$anonfun$test1LMS$1.lancet$interpreter$TestInterpreter5$$anonfun$$compute$6> - HotSpotSignature<(ILlancet/interpreter/TestInterpreter5$DecompilerLMS;)V>
      19: iload_2
      20: iconst_1
      21: iadd
      22: istore_2
      23: getstatic
      26: pop
      27: goto
      2: iload_2
      3: iload_1
      4: if_icmpge
      7: aload_0
      8: getfield
      11: iload_2
      12: aload_0
      13: getfield
      16: invokevirtual
        Call HotSpotMethod<TestInterpreter5$$anonfun$test1LMS$1.lancet$interpreter$TestInterpreter5$$anonfun$$compute$6> - HotSpotSignature<(ILlancet/interpreter/TestInterpreter5$DecompilerLMS;)V>
        0: iload_1
        1: bipush
        3: if_icmpne
        12: return
        Ret HotSpotMethod<TestInterpreter5$$anonfun$test1LMS$1.lancet$interpreter$TestInterpreter5$$anonfun$$compute$6> - HotSpotSignature<(ILlancet/interpreter/TestInterpreter5$DecompilerLMS;)V>
      19: iload_2
      20: iconst_1
      21: iadd
      22: istore_2
      23: getstatic
      26: pop
      27: goto
      2: iload_2
      3: iload_1
      4: if_icmpge
      7: aload_0
      8: getfield
      11: iload_2
      12: aload_0
      13: getfield
      16: invokevirtual
        Call HotSpotMethod<TestInterpreter5$$anonfun$test1LMS$1.lancet$interpreter$TestInterpreter5$$anonfun$$compute$6> - HotSpotSignature<(ILlancet/interpreter/TestInterpreter5$DecompilerLMS;)V>
        0: iload_1
        1: bipush
        3: if_icmpne
        12: return
        Ret HotSpotMethod<TestInterpreter5$$anonfun$test1LMS$1.lancet$interpreter$TestInterpreter5$$anonfun$$compute$6> - HotSpotSignature<(ILlancet/interpreter/TestInterpreter5$DecompilerLMS;)V>
      19: iload_2
      20: iconst_1
      21: iadd
      22: istore_2
      23: getstatic
      26: pop
      27: goto
      2: iload_2
      3: iload_1
      4: if_icmpge
      7: aload_0
      8: getfield
      11: iload_2
      12: aload_0
      13: getfield
      16: invokevirtual
        Call HotSpotMethod<TestInterpreter5$$anonfun$test1LMS$1.lancet$interpreter$TestInterpreter5$$anonfun$$compute$6> - HotSpotSignature<(ILlancet/interpreter/TestInterpreter5$DecompilerLMS;)V>
        0: iload_1
        1: bipush
        3: if_icmpne
        12: return
        Ret HotSpotMethod<TestInterpreter5$$anonfun$test1LMS$1.lancet$interpreter$TestInterpreter5$$anonfun$$compute$6> - HotSpotSignature<(ILlancet/interpreter/TestInterpreter5$DecompilerLMS;)V>
      19: iload_2
      20: iconst_1
      21: iadd
      22: istore_2
      23: getstatic
      26: pop
      27: goto
      2: iload_2
      3: iload_1
      4: if_icmpge
      7: aload_0
      8: getfield
      11: iload_2
      12: aload_0
      13: getfield
      16: invokevirtual
        Call HotSpotMethod<TestInterpreter5$$anonfun$test1LMS$1.lancet$interpreter$TestInterpreter5$$anonfun$$compute$6> - HotSpotSignature<(ILlancet/interpreter/TestInterpreter5$DecompilerLMS;)V>
        0: iload_1
        1: bipush
        3: if_icmpne
        12: return
        Ret HotSpotMethod<TestInterpreter5$$anonfun$test1LMS$1.lancet$interpreter$TestInterpreter5$$anonfun$$compute$6> - HotSpotSignature<(ILlancet/interpreter/TestInterpreter5$DecompilerLMS;)V>
      19: iload_2
      20: iconst_1
      21: iadd
      22: istore_2
      23: getstatic
      26: pop
      27: goto
      2: iload_2
      3: iload_1
      4: if_icmpge
      7: aload_0
      8: getfield
      11: iload_2
      12: aload_0
      13: getfield
      16: invokevirtual
        Call HotSpotMethod<TestInterpreter5$$anonfun$test1LMS$1.lancet$interpreter$TestInterpreter5$$anonfun$$compute$6> - HotSpotSignature<(ILlancet/interpreter/TestInterpreter5$DecompilerLMS;)V>
        0: iload_1
        1: bipush
        3: if_icmpne
        12: return
        Ret HotSpotMethod<TestInterpreter5$$anonfun$test1LMS$1.lancet$interpreter$TestInterpreter5$$anonfun$$compute$6> - HotSpotSignature<(ILlancet/interpreter/TestInterpreter5$DecompilerLMS;)V>
      19: iload_2
      20: iconst_1
      21: iadd
      22: istore_2
      23: getstatic
      26: pop
      27: goto
      2: iload_2
      3: iload_1
      4: if_icmpge
      7: aload_0
      8: getfield
      11: iload_2
      12: aload_0
      13: getfield
      16: invokevirtual
        Call HotSpotMethod<TestInterpreter5$$anonfun$test1LMS$1.lancet$interpreter$TestInterpreter5$$anonfun$$compute$6> - HotSpotSignature<(ILlancet/interpreter/TestInterpreter5$DecompilerLMS;)V>
        0: iload_1
        1: bipush
        3: if_icmpne
        12: return
        Ret HotSpotMethod<TestInterpreter5$$anonfun$test1LMS$1.lancet$interpreter$TestInterpreter5$$anonfun$$compute$6> - HotSpotSignature<(ILlancet/interpreter/TestInterpreter5$DecompilerLMS;)V>
      19: iload_2
      20: iconst_1
      21: iadd
      22: istore_2
      23: getstatic
      26: pop
      27: goto
      2: iload_2
      3: iload_1
      4: if_icmpge
      7: aload_0
      8: getfield
      11: iload_2
      12: aload_0
      13: getfield
      16: invokevirtual
        Call HotSpotMethod<TestInterpreter5$$anonfun$test1LMS$1.lancet$interpreter$TestInterpreter5$$anonfun$$compute$6> - HotSpotSignature<(ILlancet/interpreter/TestInterpreter5$DecompilerLMS;)V>
        0: iload_1
        1: bipush
        3: if_icmpne
        12: return
        Ret HotSpotMethod<TestInterpreter5$$anonfun$test1LMS$1.lancet$interpreter$TestInterpreter5$$anonfun$$compute$6> - HotSpotSignature<(ILlancet/interpreter/TestInterpreter5$DecompilerLMS;)V>
      19: iload_2
      20: iconst_1
      21: iadd
      22: istore_2
      23: getstatic
      26: pop
      27: goto
      2: iload_2
      3: iload_1
      4: if_icmpge
      7: aload_0
      8: getfield
      11: iload_2
      12: aload_0
      13: getfield
      16: invokevirtual
        Call HotSpotMethod<TestInterpreter5$$anonfun$test1LMS$1.lancet$interpreter$TestInterpreter5$$anonfun$$compute$6> - HotSpotSignature<(ILlancet/interpreter/TestInterpreter5$DecompilerLMS;)V>
        0: iload_1
        1: bipush
        3: if_icmpne
        12: return
        Ret HotSpotMethod<TestInterpreter5$$anonfun$test1LMS$1.lancet$interpreter$TestInterpreter5$$anonfun$$compute$6> - HotSpotSignature<(ILlancet/interpreter/TestInterpreter5$DecompilerLMS;)V>
      19: iload_2
      20: iconst_1
      21: iadd
      22: istore_2
      23: getstatic
      26: pop
      27: goto
      2: iload_2
      3: iload_1
      4: if_icmpge
      30: iload_2
      31: ireturn
      Ret HotSpotMethod<TestInterpreter5$$anonfun$test1LMS$1$$anonfun$6.apply$mcII$sp> - HotSpotSignature<(I)I>
    5: ireturn
    Ret HotSpotMethod<TestInterpreter5$$anonfun$test1LMS$1$$anonfun$6.apply> - HotSpotSignature<(I)I>
-- done interpreting
HotSpotMethod<TestInterpreter5$$anonfun$test1LMS$1.lancet$interpreter$TestInterpreter5$$anonfun$$compute$6>
null,null,null,null,null
root:
HotSpotMethod<BytecodeInterpreter_Exec.execute>
lancet.interpreter.TestInterpreter5$DecompilerLMS@40dfc732,HotSpotMethod<TestInterpreter5$$anonfun$test1LMS$1$$anonfun$6.apply>,[Lscala.virtualization.lms.internal.Expressions$Exp;@71f42120,100,null,null,null,null,null
result: 100
100
