Executing root method HotSpotMethod<TestInterpreter5$$anonfun$test1a$1$$anonfun$1.apply>
    RootCall HotSpotMethod<TestInterpreter5$$anonfun$test1a$1$$anonfun$1.apply> - HotSpotSignature<(I)I>
    0: aload_0
    1: iload_1
    2: invokevirtual
      Call HotSpotMethod<TestInterpreter5$$anonfun$test1a$1$$anonfun$1.apply$mcII$sp> - HotSpotSignature<(I)I>
      0: iconst_0
      1: istore_2
      2: iload_2
      3: iload_1
      4: if_icmpge
      7: aload_0
      8: getfield
      11: iload_2
      12: aload_0
      13: getfield
      16: invokevirtual
        Call HotSpotMethod<TestInterpreter5$$anonfun$test1a$1.lancet$interpreter$TestInterpreter5$$anonfun$$compute$1> - HotSpotSignature<(ILlancet/interpreter/TestInterpreter5$Decompiler;)V>
        0: iload_1
        1: bipush
        3: if_icmpne
        10: return
        Ret HotSpotMethod<TestInterpreter5$$anonfun$test1a$1.lancet$interpreter$TestInterpreter5$$anonfun$$compute$1> - HotSpotSignature<(ILlancet/interpreter/TestInterpreter5$Decompiler;)V>
      19: iload_2
      20: iconst_1
      21: iadd
      22: istore_2
      23: getstatic
      26: pop
      27: goto
      2: iload_2
      3: iload_1
      4: if_icmpge
      7: aload_0
      8: getfield
      11: iload_2
      12: aload_0
      13: getfield
      16: invokevirtual
        Call HotSpotMethod<TestInterpreter5$$anonfun$test1a$1.lancet$interpreter$TestInterpreter5$$anonfun$$compute$1> - HotSpotSignature<(ILlancet/interpreter/TestInterpreter5$Decompiler;)V>
        0: iload_1
        1: bipush
        3: if_icmpne
        10: return
        Ret HotSpotMethod<TestInterpreter5$$anonfun$test1a$1.lancet$interpreter$TestInterpreter5$$anonfun$$compute$1> - HotSpotSignature<(ILlancet/interpreter/TestInterpreter5$Decompiler;)V>
      19: iload_2
      20: iconst_1
      21: iadd
      22: istore_2
      23: getstatic
      26: pop
      27: goto
      2: iload_2
      3: iload_1
      4: if_icmpge
      7: aload_0
      8: getfield
      11: iload_2
      12: aload_0
      13: getfield
      16: invokevirtual
        Call HotSpotMethod<TestInterpreter5$$anonfun$test1a$1.lancet$interpreter$TestInterpreter5$$anonfun$$compute$1> - HotSpotSignature<(ILlancet/interpreter/TestInterpreter5$Decompiler;)V>
        0: iload_1
        1: bipush
        3: if_icmpne
        10: return
        Ret HotSpotMethod<TestInterpreter5$$anonfun$test1a$1.lancet$interpreter$TestInterpreter5$$anonfun$$compute$1> - HotSpotSignature<(ILlancet/interpreter/TestInterpreter5$Decompiler;)V>
      19: iload_2
      20: iconst_1
      21: iadd
      22: istore_2
      23: getstatic
      26: pop
      27: goto
      2: iload_2
      3: iload_1
      4: if_icmpge
      7: aload_0
      8: getfield
      11: iload_2
      12: aload_0
      13: getfield
      16: invokevirtual
        Call HotSpotMethod<TestInterpreter5$$anonfun$test1a$1.lancet$interpreter$TestInterpreter5$$anonfun$$compute$1> - HotSpotSignature<(ILlancet/interpreter/TestInterpreter5$Decompiler;)V>
        0: iload_1
        1: bipush
        3: if_icmpne
        10: return
        Ret HotSpotMethod<TestInterpreter5$$anonfun$test1a$1.lancet$interpreter$TestInterpreter5$$anonfun$$compute$1> - HotSpotSignature<(ILlancet/interpreter/TestInterpreter5$Decompiler;)V>
      19: iload_2
      20: iconst_1
      21: iadd
      22: istore_2
      23: getstatic
      26: pop
      27: goto
      2: iload_2
      3: iload_1
      4: if_icmpge
      7: aload_0
      8: getfield
      11: iload_2
      12: aload_0
      13: getfield
      16: invokevirtual
        Call HotSpotMethod<TestInterpreter5$$anonfun$test1a$1.lancet$interpreter$TestInterpreter5$$anonfun$$compute$1> - HotSpotSignature<(ILlancet/interpreter/TestInterpreter5$Decompiler;)V>
        0: iload_1
        1: bipush
        3: if_icmpne
        10: return
        Ret HotSpotMethod<TestInterpreter5$$anonfun$test1a$1.lancet$interpreter$TestInterpreter5$$anonfun$$compute$1> - HotSpotSignature<(ILlancet/interpreter/TestInterpreter5$Decompiler;)V>
      19: iload_2
      20: iconst_1
      21: iadd
      22: istore_2
      23: getstatic
      26: pop
      27: goto
      2: iload_2
      3: iload_1
      4: if_icmpge
      7: aload_0
      8: getfield
      11: iload_2
      12: aload_0
      13: getfield
      16: invokevirtual
        Call HotSpotMethod<TestInterpreter5$$anonfun$test1a$1.lancet$interpreter$TestInterpreter5$$anonfun$$compute$1> - HotSpotSignature<(ILlancet/interpreter/TestInterpreter5$Decompiler;)V>
        0: iload_1
        1: bipush
        3: if_icmpne
        10: return
        Ret HotSpotMethod<TestInterpreter5$$anonfun$test1a$1.lancet$interpreter$TestInterpreter5$$anonfun$$compute$1> - HotSpotSignature<(ILlancet/interpreter/TestInterpreter5$Decompiler;)V>
      19: iload_2
      20: iconst_1
      21: iadd
      22: istore_2
      23: getstatic
      26: pop
      27: goto
      2: iload_2
      3: iload_1
      4: if_icmpge
      7: aload_0
      8: getfield
      11: iload_2
      12: aload_0
      13: getfield
      16: invokevirtual
        Call HotSpotMethod<TestInterpreter5$$anonfun$test1a$1.lancet$interpreter$TestInterpreter5$$anonfun$$compute$1> - HotSpotSignature<(ILlancet/interpreter/TestInterpreter5$Decompiler;)V>
        0: iload_1
        1: bipush
        3: if_icmpne
        10: return
        Ret HotSpotMethod<TestInterpreter5$$anonfun$test1a$1.lancet$interpreter$TestInterpreter5$$anonfun$$compute$1> - HotSpotSignature<(ILlancet/interpreter/TestInterpreter5$Decompiler;)V>
      19: iload_2
      20: iconst_1
      21: iadd
      22: istore_2
      23: getstatic
      26: pop
      27: goto
      2: iload_2
      3: iload_1
      4: if_icmpge
      7: aload_0
      8: getfield
      11: iload_2
      12: aload_0
      13: getfield
      16: invokevirtual
        Call HotSpotMethod<TestInterpreter5$$anonfun$test1a$1.lancet$interpreter$TestInterpreter5$$anonfun$$compute$1> - HotSpotSignature<(ILlancet/interpreter/TestInterpreter5$Decompiler;)V>
        0: iload_1
        1: bipush
        3: if_icmpne
        10: return
        Ret HotSpotMethod<TestInterpreter5$$anonfun$test1a$1.lancet$interpreter$TestInterpreter5$$anonfun$$compute$1> - HotSpotSignature<(ILlancet/interpreter/TestInterpreter5$Decompiler;)V>
      19: iload_2
      20: iconst_1
      21: iadd
      22: istore_2
      23: getstatic
      26: pop
      27: goto
      2: iload_2
      3: iload_1
      4: if_icmpge
      7: aload_0
      8: getfield
      11: iload_2
      12: aload_0
      13: getfield
      16: invokevirtual
        Call HotSpotMethod<TestInterpreter5$$anonfun$test1a$1.lancet$interpreter$TestInterpreter5$$anonfun$$compute$1> - HotSpotSignature<(ILlancet/interpreter/TestInterpreter5$Decompiler;)V>
        0: iload_1
        1: bipush
        3: if_icmpne
        10: return
        Ret HotSpotMethod<TestInterpreter5$$anonfun$test1a$1.lancet$interpreter$TestInterpreter5$$anonfun$$compute$1> - HotSpotSignature<(ILlancet/interpreter/TestInterpreter5$Decompiler;)V>
      19: iload_2
      20: iconst_1
      21: iadd
      22: istore_2
      23: getstatic
      26: pop
      27: goto
      2: iload_2
      3: iload_1
      4: if_icmpge
      7: aload_0
      8: getfield
      11: iload_2
      12: aload_0
      13: getfield
      16: invokevirtual
        Call HotSpotMethod<TestInterpreter5$$anonfun$test1a$1.lancet$interpreter$TestInterpreter5$$anonfun$$compute$1> - HotSpotSignature<(ILlancet/interpreter/TestInterpreter5$Decompiler;)V>
        0: iload_1
        1: bipush
        3: if_icmpne
        10: return
        Ret HotSpotMethod<TestInterpreter5$$anonfun$test1a$1.lancet$interpreter$TestInterpreter5$$anonfun$$compute$1> - HotSpotSignature<(ILlancet/interpreter/TestInterpreter5$Decompiler;)V>
      19: iload_2
      20: iconst_1
      21: iadd
      22: istore_2
      23: getstatic
      26: pop
      27: goto
      2: iload_2
      3: iload_1
      4: if_icmpge
      7: aload_0
      8: getfield
      11: iload_2
      12: aload_0
      13: getfield
      16: invokevirtual
        Call HotSpotMethod<TestInterpreter5$$anonfun$test1a$1.lancet$interpreter$TestInterpreter5$$anonfun$$compute$1> - HotSpotSignature<(ILlancet/interpreter/TestInterpreter5$Decompiler;)V>
        0: iload_1
        1: bipush
        3: if_icmpne
        10: return
        Ret HotSpotMethod<TestInterpreter5$$anonfun$test1a$1.lancet$interpreter$TestInterpreter5$$anonfun$$compute$1> - HotSpotSignature<(ILlancet/interpreter/TestInterpreter5$Decompiler;)V>
      19: iload_2
      20: iconst_1
      21: iadd
      22: istore_2
      23: getstatic
      26: pop
      27: goto
      2: iload_2
      3: iload_1
      4: if_icmpge
      7: aload_0
      8: getfield
      11: iload_2
      12: aload_0
      13: getfield
      16: invokevirtual
        Call HotSpotMethod<TestInterpreter5$$anonfun$test1a$1.lancet$interpreter$TestInterpreter5$$anonfun$$compute$1> - HotSpotSignature<(ILlancet/interpreter/TestInterpreter5$Decompiler;)V>
        0: iload_1
        1: bipush
        3: if_icmpne
        10: return
        Ret HotSpotMethod<TestInterpreter5$$anonfun$test1a$1.lancet$interpreter$TestInterpreter5$$anonfun$$compute$1> - HotSpotSignature<(ILlancet/interpreter/TestInterpreter5$Decompiler;)V>
      19: iload_2
      20: iconst_1
      21: iadd
      22: istore_2
      23: getstatic
      26: pop
      27: goto
      2: iload_2
      3: iload_1
      4: if_icmpge
      7: aload_0
      8: getfield
      11: iload_2
      12: aload_0
      13: getfield
      16: invokevirtual
        Call HotSpotMethod<TestInterpreter5$$anonfun$test1a$1.lancet$interpreter$TestInterpreter5$$anonfun$$compute$1> - HotSpotSignature<(ILlancet/interpreter/TestInterpreter5$Decompiler;)V>
        0: iload_1
        1: bipush
        3: if_icmpne
        10: return
        Ret HotSpotMethod<TestInterpreter5$$anonfun$test1a$1.lancet$interpreter$TestInterpreter5$$anonfun$$compute$1> - HotSpotSignature<(ILlancet/interpreter/TestInterpreter5$Decompiler;)V>
      19: iload_2
      20: iconst_1
      21: iadd
      22: istore_2
      23: getstatic
      26: pop
      27: goto
      2: iload_2
      3: iload_1
      4: if_icmpge
      7: aload_0
      8: getfield
      11: iload_2
      12: aload_0
      13: getfield
      16: invokevirtual
        Call HotSpotMethod<TestInterpreter5$$anonfun$test1a$1.lancet$interpreter$TestInterpreter5$$anonfun$$compute$1> - HotSpotSignature<(ILlancet/interpreter/TestInterpreter5$Decompiler;)V>
        0: iload_1
        1: bipush
        3: if_icmpne
        10: return
        Ret HotSpotMethod<TestInterpreter5$$anonfun$test1a$1.lancet$interpreter$TestInterpreter5$$anonfun$$compute$1> - HotSpotSignature<(ILlancet/interpreter/TestInterpreter5$Decompiler;)V>
      19: iload_2
      20: iconst_1
      21: iadd
      22: istore_2
      23: getstatic
      26: pop
      27: goto
      2: iload_2
      3: iload_1
      4: if_icmpge
      7: aload_0
      8: getfield
      11: iload_2
      12: aload_0
      13: getfield
      16: invokevirtual
        Call HotSpotMethod<TestInterpreter5$$anonfun$test1a$1.lancet$interpreter$TestInterpreter5$$anonfun$$compute$1> - HotSpotSignature<(ILlancet/interpreter/TestInterpreter5$Decompiler;)V>
        0: iload_1
        1: bipush
        3: if_icmpne
        10: return
        Ret HotSpotMethod<TestInterpreter5$$anonfun$test1a$1.lancet$interpreter$TestInterpreter5$$anonfun$$compute$1> - HotSpotSignature<(ILlancet/interpreter/TestInterpreter5$Decompiler;)V>
      19: iload_2
      20: iconst_1
      21: iadd
      22: istore_2
      23: getstatic
      26: pop
      27: goto
      2: iload_2
      3: iload_1
      4: if_icmpge
      7: aload_0
      8: getfield
      11: iload_2
      12: aload_0
      13: getfield
      16: invokevirtual
        Call HotSpotMethod<TestInterpreter5$$anonfun$test1a$1.lancet$interpreter$TestInterpreter5$$anonfun$$compute$1> - HotSpotSignature<(ILlancet/interpreter/TestInterpreter5$Decompiler;)V>
        0: iload_1
        1: bipush
        3: if_icmpne
        10: return
        Ret HotSpotMethod<TestInterpreter5$$anonfun$test1a$1.lancet$interpreter$TestInterpreter5$$anonfun$$compute$1> - HotSpotSignature<(ILlancet/interpreter/TestInterpreter5$Decompiler;)V>
      19: iload_2
      20: iconst_1
      21: iadd
      22: istore_2
      23: getstatic
      26: pop
      27: goto
      2: iload_2
      3: iload_1
      4: if_icmpge
      7: aload_0
      8: getfield
      11: iload_2
      12: aload_0
      13: getfield
      16: invokevirtual
        Call HotSpotMethod<TestInterpreter5$$anonfun$test1a$1.lancet$interpreter$TestInterpreter5$$anonfun$$compute$1> - HotSpotSignature<(ILlancet/interpreter/TestInterpreter5$Decompiler;)V>
        0: iload_1
        1: bipush
        3: if_icmpne
        10: return
        Ret HotSpotMethod<TestInterpreter5$$anonfun$test1a$1.lancet$interpreter$TestInterpreter5$$anonfun$$compute$1> - HotSpotSignature<(ILlancet/interpreter/TestInterpreter5$Decompiler;)V>
      19: iload_2
      20: iconst_1
      21: iadd
      22: istore_2
      23: getstatic
      26: pop
      27: goto
      2: iload_2
      3: iload_1
      4: if_icmpge
      7: aload_0
      8: getfield
      11: iload_2
      12: aload_0
      13: getfield
      16: invokevirtual
        Call HotSpotMethod<TestInterpreter5$$anonfun$test1a$1.lancet$interpreter$TestInterpreter5$$anonfun$$compute$1> - HotSpotSignature<(ILlancet/interpreter/TestInterpreter5$Decompiler;)V>
        0: iload_1
        1: bipush
        3: if_icmpne
        10: return
        Ret HotSpotMethod<TestInterpreter5$$anonfun$test1a$1.lancet$interpreter$TestInterpreter5$$anonfun$$compute$1> - HotSpotSignature<(ILlancet/interpreter/TestInterpreter5$Decompiler;)V>
      19: iload_2
      20: iconst_1
      21: iadd
      22: istore_2
      23: getstatic
      26: pop
      27: goto
      2: iload_2
      3: iload_1
      4: if_icmpge
      7: aload_0
      8: getfield
      11: iload_2
      12: aload_0
      13: getfield
      16: invokevirtual
        Call HotSpotMethod<TestInterpreter5$$anonfun$test1a$1.lancet$interpreter$TestInterpreter5$$anonfun$$compute$1> - HotSpotSignature<(ILlancet/interpreter/TestInterpreter5$Decompiler;)V>
        0: iload_1
        1: bipush
        3: if_icmpne
        10: return
        Ret HotSpotMethod<TestInterpreter5$$anonfun$test1a$1.lancet$interpreter$TestInterpreter5$$anonfun$$compute$1> - HotSpotSignature<(ILlancet/interpreter/TestInterpreter5$Decompiler;)V>
      19: iload_2
      20: iconst_1
      21: iadd
      22: istore_2
      23: getstatic
      26: pop
      27: goto
      2: iload_2
      3: iload_1
      4: if_icmpge
      7: aload_0
      8: getfield
      11: iload_2
      12: aload_0
      13: getfield
      16: invokevirtual
        Call HotSpotMethod<TestInterpreter5$$anonfun$test1a$1.lancet$interpreter$TestInterpreter5$$anonfun$$compute$1> - HotSpotSignature<(ILlancet/interpreter/TestInterpreter5$Decompiler;)V>
        0: iload_1
        1: bipush
        3: if_icmpne
        10: return
        Ret HotSpotMethod<TestInterpreter5$$anonfun$test1a$1.lancet$interpreter$TestInterpreter5$$anonfun$$compute$1> - HotSpotSignature<(ILlancet/interpreter/TestInterpreter5$Decompiler;)V>
      19: iload_2
      20: iconst_1
      21: iadd
      22: istore_2
      23: getstatic
      26: pop
      27: goto
      2: iload_2
      3: iload_1
      4: if_icmpge
      7: aload_0
      8: getfield
      11: iload_2
      12: aload_0
      13: getfield
      16: invokevirtual
        Call HotSpotMethod<TestInterpreter5$$anonfun$test1a$1.lancet$interpreter$TestInterpreter5$$anonfun$$compute$1> - HotSpotSignature<(ILlancet/interpreter/TestInterpreter5$Decompiler;)V>
        0: iload_1
        1: bipush
        3: if_icmpne
        10: return
        Ret HotSpotMethod<TestInterpreter5$$anonfun$test1a$1.lancet$interpreter$TestInterpreter5$$anonfun$$compute$1> - HotSpotSignature<(ILlancet/interpreter/TestInterpreter5$Decompiler;)V>
      19: iload_2
      20: iconst_1
      21: iadd
      22: istore_2
      23: getstatic
      26: pop
      27: goto
      2: iload_2
      3: iload_1
      4: if_icmpge
      7: aload_0
      8: getfield
      11: iload_2
      12: aload_0
      13: getfield
      16: invokevirtual
        Call HotSpotMethod<TestInterpreter5$$anonfun$test1a$1.lancet$interpreter$TestInterpreter5$$anonfun$$compute$1> - HotSpotSignature<(ILlancet/interpreter/TestInterpreter5$Decompiler;)V>
        0: iload_1
        1: bipush
        3: if_icmpne
        10: return
        Ret HotSpotMethod<TestInterpreter5$$anonfun$test1a$1.lancet$interpreter$TestInterpreter5$$anonfun$$compute$1> - HotSpotSignature<(ILlancet/interpreter/TestInterpreter5$Decompiler;)V>
      19: iload_2
      20: iconst_1
      21: iadd
      22: istore_2
      23: getstatic
      26: pop
      27: goto
      2: iload_2
      3: iload_1
      4: if_icmpge
      7: aload_0
      8: getfield
      11: iload_2
      12: aload_0
      13: getfield
      16: invokevirtual
        Call HotSpotMethod<TestInterpreter5$$anonfun$test1a$1.lancet$interpreter$TestInterpreter5$$anonfun$$compute$1> - HotSpotSignature<(ILlancet/interpreter/TestInterpreter5$Decompiler;)V>
        0: iload_1
        1: bipush
        3: if_icmpne
        10: return
        Ret HotSpotMethod<TestInterpreter5$$anonfun$test1a$1.lancet$interpreter$TestInterpreter5$$anonfun$$compute$1> - HotSpotSignature<(ILlancet/interpreter/TestInterpreter5$Decompiler;)V>
      19: iload_2
      20: iconst_1
      21: iadd
      22: istore_2
      23: getstatic
      26: pop
      27: goto
      2: iload_2
      3: iload_1
      4: if_icmpge
      7: aload_0
      8: getfield
      11: iload_2
      12: aload_0
      13: getfield
      16: invokevirtual
        Call HotSpotMethod<TestInterpreter5$$anonfun$test1a$1.lancet$interpreter$TestInterpreter5$$anonfun$$compute$1> - HotSpotSignature<(ILlancet/interpreter/TestInterpreter5$Decompiler;)V>
        0: iload_1
        1: bipush
        3: if_icmpne
        10: return
        Ret HotSpotMethod<TestInterpreter5$$anonfun$test1a$1.lancet$interpreter$TestInterpreter5$$anonfun$$compute$1> - HotSpotSignature<(ILlancet/interpreter/TestInterpreter5$Decompiler;)V>
      19: iload_2
      20: iconst_1
      21: iadd
      22: istore_2
      23: getstatic
      26: pop
      27: goto
      2: iload_2
      3: iload_1
      4: if_icmpge
      7: aload_0
      8: getfield
      11: iload_2
      12: aload_0
      13: getfield
      16: invokevirtual
        Call HotSpotMethod<TestInterpreter5$$anonfun$test1a$1.lancet$interpreter$TestInterpreter5$$anonfun$$compute$1> - HotSpotSignature<(ILlancet/interpreter/TestInterpreter5$Decompiler;)V>
        0: iload_1
        1: bipush
        3: if_icmpne
        10: return
        Ret HotSpotMethod<TestInterpreter5$$anonfun$test1a$1.lancet$interpreter$TestInterpreter5$$anonfun$$compute$1> - HotSpotSignature<(ILlancet/interpreter/TestInterpreter5$Decompiler;)V>
      19: iload_2
      20: iconst_1
      21: iadd
      22: istore_2
      23: getstatic
      26: pop
      27: goto
      2: iload_2
      3: iload_1
      4: if_icmpge
      7: aload_0
      8: getfield
      11: iload_2
      12: aload_0
      13: getfield
      16: invokevirtual
        Call HotSpotMethod<TestInterpreter5$$anonfun$test1a$1.lancet$interpreter$TestInterpreter5$$anonfun$$compute$1> - HotSpotSignature<(ILlancet/interpreter/TestInterpreter5$Decompiler;)V>
        0: iload_1
        1: bipush
        3: if_icmpne
        10: return
        Ret HotSpotMethod<TestInterpreter5$$anonfun$test1a$1.lancet$interpreter$TestInterpreter5$$anonfun$$compute$1> - HotSpotSignature<(ILlancet/interpreter/TestInterpreter5$Decompiler;)V>
      19: iload_2
      20: iconst_1
      21: iadd
      22: istore_2
      23: getstatic
      26: pop
      27: goto
      2: iload_2
      3: iload_1
      4: if_icmpge
      7: aload_0
      8: getfield
      11: iload_2
      12: aload_0
      13: getfield
      16: invokevirtual
        Call HotSpotMethod<TestInterpreter5$$anonfun$test1a$1.lancet$interpreter$TestInterpreter5$$anonfun$$compute$1> - HotSpotSignature<(ILlancet/interpreter/TestInterpreter5$Decompiler;)V>
        0: iload_1
        1: bipush
        3: if_icmpne
        10: return
        Ret HotSpotMethod<TestInterpreter5$$anonfun$test1a$1.lancet$interpreter$TestInterpreter5$$anonfun$$compute$1> - HotSpotSignature<(ILlancet/interpreter/TestInterpreter5$Decompiler;)V>
      19: iload_2
      20: iconst_1
      21: iadd
      22: istore_2
      23: getstatic
      26: pop
      27: goto
      2: iload_2
      3: iload_1
      4: if_icmpge
      7: aload_0
      8: getfield
      11: iload_2
      12: aload_0
      13: getfield
      16: invokevirtual
        Call HotSpotMethod<TestInterpreter5$$anonfun$test1a$1.lancet$interpreter$TestInterpreter5$$anonfun$$compute$1> - HotSpotSignature<(ILlancet/interpreter/TestInterpreter5$Decompiler;)V>
        0: iload_1
        1: bipush
        3: if_icmpne
        10: return
        Ret HotSpotMethod<TestInterpreter5$$anonfun$test1a$1.lancet$interpreter$TestInterpreter5$$anonfun$$compute$1> - HotSpotSignature<(ILlancet/interpreter/TestInterpreter5$Decompiler;)V>
      19: iload_2
      20: iconst_1
      21: iadd
      22: istore_2
      23: getstatic
      26: pop
      27: goto
      2: iload_2
      3: iload_1
      4: if_icmpge
      7: aload_0
      8: getfield
      11: iload_2
      12: aload_0
      13: getfield
      16: invokevirtual
        Call HotSpotMethod<TestInterpreter5$$anonfun$test1a$1.lancet$interpreter$TestInterpreter5$$anonfun$$compute$1> - HotSpotSignature<(ILlancet/interpreter/TestInterpreter5$Decompiler;)V>
        0: iload_1
        1: bipush
        3: if_icmpne
        10: return
        Ret HotSpotMethod<TestInterpreter5$$anonfun$test1a$1.lancet$interpreter$TestInterpreter5$$anonfun$$compute$1> - HotSpotSignature<(ILlancet/interpreter/TestInterpreter5$Decompiler;)V>
      19: iload_2
      20: iconst_1
      21: iadd
      22: istore_2
      23: getstatic
      26: pop
      27: goto
      2: iload_2
      3: iload_1
      4: if_icmpge
      7: aload_0
      8: getfield
      11: iload_2
      12: aload_0
      13: getfield
      16: invokevirtual
        Call HotSpotMethod<TestInterpreter5$$anonfun$test1a$1.lancet$interpreter$TestInterpreter5$$anonfun$$compute$1> - HotSpotSignature<(ILlancet/interpreter/TestInterpreter5$Decompiler;)V>
        0: iload_1
        1: bipush
        3: if_icmpne
        10: return
        Ret HotSpotMethod<TestInterpreter5$$anonfun$test1a$1.lancet$interpreter$TestInterpreter5$$anonfun$$compute$1> - HotSpotSignature<(ILlancet/interpreter/TestInterpreter5$Decompiler;)V>
      19: iload_2
      20: iconst_1
      21: iadd
      22: istore_2
      23: getstatic
      26: pop
      27: goto
      2: iload_2
      3: iload_1
      4: if_icmpge
      7: aload_0
      8: getfield
      11: iload_2
      12: aload_0
      13: getfield
      16: invokevirtual
        Call HotSpotMethod<TestInterpreter5$$anonfun$test1a$1.lancet$interpreter$TestInterpreter5$$anonfun$$compute$1> - HotSpotSignature<(ILlancet/interpreter/TestInterpreter5$Decompiler;)V>
        0: iload_1
        1: bipush
        3: if_icmpne
        10: return
        Ret HotSpotMethod<TestInterpreter5$$anonfun$test1a$1.lancet$interpreter$TestInterpreter5$$anonfun$$compute$1> - HotSpotSignature<(ILlancet/interpreter/TestInterpreter5$Decompiler;)V>
      19: iload_2
      20: iconst_1
      21: iadd
      22: istore_2
      23: getstatic
      26: pop
      27: goto
      2: iload_2
      3: iload_1
      4: if_icmpge
      7: aload_0
      8: getfield
      11: iload_2
      12: aload_0
      13: getfield
      16: invokevirtual
        Call HotSpotMethod<TestInterpreter5$$anonfun$test1a$1.lancet$interpreter$TestInterpreter5$$anonfun$$compute$1> - HotSpotSignature<(ILlancet/interpreter/TestInterpreter5$Decompiler;)V>
        0: iload_1
        1: bipush
        3: if_icmpne
        10: return
        Ret HotSpotMethod<TestInterpreter5$$anonfun$test1a$1.lancet$interpreter$TestInterpreter5$$anonfun$$compute$1> - HotSpotSignature<(ILlancet/interpreter/TestInterpreter5$Decompiler;)V>
      19: iload_2
      20: iconst_1
      21: iadd
      22: istore_2
      23: getstatic
      26: pop
      27: goto
      2: iload_2
      3: iload_1
      4: if_icmpge
      7: aload_0
      8: getfield
      11: iload_2
      12: aload_0
      13: getfield
      16: invokevirtual
        Call HotSpotMethod<TestInterpreter5$$anonfun$test1a$1.lancet$interpreter$TestInterpreter5$$anonfun$$compute$1> - HotSpotSignature<(ILlancet/interpreter/TestInterpreter5$Decompiler;)V>
        0: iload_1
        1: bipush
        3: if_icmpne
        10: return
        Ret HotSpotMethod<TestInterpreter5$$anonfun$test1a$1.lancet$interpreter$TestInterpreter5$$anonfun$$compute$1> - HotSpotSignature<(ILlancet/interpreter/TestInterpreter5$Decompiler;)V>
      19: iload_2
      20: iconst_1
      21: iadd
      22: istore_2
      23: getstatic
      26: pop
      27: goto
      2: iload_2
      3: iload_1
      4: if_icmpge
      7: aload_0
      8: getfield
      11: iload_2
      12: aload_0
      13: getfield
      16: invokevirtual
        Call HotSpotMethod<TestInterpreter5$$anonfun$test1a$1.lancet$interpreter$TestInterpreter5$$anonfun$$compute$1> - HotSpotSignature<(ILlancet/interpreter/TestInterpreter5$Decompiler;)V>
        0: iload_1
        1: bipush
        3: if_icmpne
        10: return
        Ret HotSpotMethod<TestInterpreter5$$anonfun$test1a$1.lancet$interpreter$TestInterpreter5$$anonfun$$compute$1> - HotSpotSignature<(ILlancet/interpreter/TestInterpreter5$Decompiler;)V>
      19: iload_2
      20: iconst_1
      21: iadd
      22: istore_2
      23: getstatic
      26: pop
      27: goto
      2: iload_2
      3: iload_1
      4: if_icmpge
      7: aload_0
      8: getfield
      11: iload_2
      12: aload_0
      13: getfield
      16: invokevirtual
        Call HotSpotMethod<TestInterpreter5$$anonfun$test1a$1.lancet$interpreter$TestInterpreter5$$anonfun$$compute$1> - HotSpotSignature<(ILlancet/interpreter/TestInterpreter5$Decompiler;)V>
        0: iload_1
        1: bipush
        3: if_icmpne
        10: return
        Ret HotSpotMethod<TestInterpreter5$$anonfun$test1a$1.lancet$interpreter$TestInterpreter5$$anonfun$$compute$1> - HotSpotSignature<(ILlancet/interpreter/TestInterpreter5$Decompiler;)V>
      19: iload_2
      20: iconst_1
      21: iadd
      22: istore_2
      23: getstatic
      26: pop
      27: goto
      2: iload_2
      3: iload_1
      4: if_icmpge
      7: aload_0
      8: getfield
      11: iload_2
      12: aload_0
      13: getfield
      16: invokevirtual
        Call HotSpotMethod<TestInterpreter5$$anonfun$test1a$1.lancet$interpreter$TestInterpreter5$$anonfun$$compute$1> - HotSpotSignature<(ILlancet/interpreter/TestInterpreter5$Decompiler;)V>
        0: iload_1
        1: bipush
        3: if_icmpne
        10: return
        Ret HotSpotMethod<TestInterpreter5$$anonfun$test1a$1.lancet$interpreter$TestInterpreter5$$anonfun$$compute$1> - HotSpotSignature<(ILlancet/interpreter/TestInterpreter5$Decompiler;)V>
      19: iload_2
      20: iconst_1
      21: iadd
      22: istore_2
      23: getstatic
      26: pop
      27: goto
      2: iload_2
      3: iload_1
      4: if_icmpge
      7: aload_0
      8: getfield
      11: iload_2
      12: aload_0
      13: getfield
      16: invokevirtual
        Call HotSpotMethod<TestInterpreter5$$anonfun$test1a$1.lancet$interpreter$TestInterpreter5$$anonfun$$compute$1> - HotSpotSignature<(ILlancet/interpreter/TestInterpreter5$Decompiler;)V>
        0: iload_1
        1: bipush
        3: if_icmpne
        10: return
        Ret HotSpotMethod<TestInterpreter5$$anonfun$test1a$1.lancet$interpreter$TestInterpreter5$$anonfun$$compute$1> - HotSpotSignature<(ILlancet/interpreter/TestInterpreter5$Decompiler;)V>
      19: iload_2
      20: iconst_1
      21: iadd
      22: istore_2
      23: getstatic
      26: pop
      27: goto
      2: iload_2
      3: iload_1
      4: if_icmpge
      7: aload_0
      8: getfield
      11: iload_2
      12: aload_0
      13: getfield
      16: invokevirtual
        Call HotSpotMethod<TestInterpreter5$$anonfun$test1a$1.lancet$interpreter$TestInterpreter5$$anonfun$$compute$1> - HotSpotSignature<(ILlancet/interpreter/TestInterpreter5$Decompiler;)V>
        0: iload_1
        1: bipush
        3: if_icmpne
        10: return
        Ret HotSpotMethod<TestInterpreter5$$anonfun$test1a$1.lancet$interpreter$TestInterpreter5$$anonfun$$compute$1> - HotSpotSignature<(ILlancet/interpreter/TestInterpreter5$Decompiler;)V>
      19: iload_2
      20: iconst_1
      21: iadd
      22: istore_2
      23: getstatic
      26: pop
      27: goto
      2: iload_2
      3: iload_1
      4: if_icmpge
      7: aload_0
      8: getfield
      11: iload_2
      12: aload_0
      13: getfield
      16: invokevirtual
        Call HotSpotMethod<TestInterpreter5$$anonfun$test1a$1.lancet$interpreter$TestInterpreter5$$anonfun$$compute$1> - HotSpotSignature<(ILlancet/interpreter/TestInterpreter5$Decompiler;)V>
        0: iload_1
        1: bipush
        3: if_icmpne
        10: return
        Ret HotSpotMethod<TestInterpreter5$$anonfun$test1a$1.lancet$interpreter$TestInterpreter5$$anonfun$$compute$1> - HotSpotSignature<(ILlancet/interpreter/TestInterpreter5$Decompiler;)V>
      19: iload_2
      20: iconst_1
      21: iadd
      22: istore_2
      23: getstatic
      26: pop
      27: goto
      2: iload_2
      3: iload_1
      4: if_icmpge
      7: aload_0
      8: getfield
      11: iload_2
      12: aload_0
      13: getfield
      16: invokevirtual
        Call HotSpotMethod<TestInterpreter5$$anonfun$test1a$1.lancet$interpreter$TestInterpreter5$$anonfun$$compute$1> - HotSpotSignature<(ILlancet/interpreter/TestInterpreter5$Decompiler;)V>
        0: iload_1
        1: bipush
        3: if_icmpne
        10: return
        Ret HotSpotMethod<TestInterpreter5$$anonfun$test1a$1.lancet$interpreter$TestInterpreter5$$anonfun$$compute$1> - HotSpotSignature<(ILlancet/interpreter/TestInterpreter5$Decompiler;)V>
      19: iload_2
      20: iconst_1
      21: iadd
      22: istore_2
      23: getstatic
      26: pop
      27: goto
      2: iload_2
      3: iload_1
      4: if_icmpge
      7: aload_0
      8: getfield
      11: iload_2
      12: aload_0
      13: getfield
      16: invokevirtual
        Call HotSpotMethod<TestInterpreter5$$anonfun$test1a$1.lancet$interpreter$TestInterpreter5$$anonfun$$compute$1> - HotSpotSignature<(ILlancet/interpreter/TestInterpreter5$Decompiler;)V>
        0: iload_1
        1: bipush
        3: if_icmpne
        10: return
        Ret HotSpotMethod<TestInterpreter5$$anonfun$test1a$1.lancet$interpreter$TestInterpreter5$$anonfun$$compute$1> - HotSpotSignature<(ILlancet/interpreter/TestInterpreter5$Decompiler;)V>
      19: iload_2
      20: iconst_1
      21: iadd
      22: istore_2
      23: getstatic
      26: pop
      27: goto
      2: iload_2
      3: iload_1
      4: if_icmpge
      7: aload_0
      8: getfield
      11: iload_2
      12: aload_0
      13: getfield
      16: invokevirtual
        Call HotSpotMethod<TestInterpreter5$$anonfun$test1a$1.lancet$interpreter$TestInterpreter5$$anonfun$$compute$1> - HotSpotSignature<(ILlancet/interpreter/TestInterpreter5$Decompiler;)V>
        0: iload_1
        1: bipush
        3: if_icmpne
        10: return
        Ret HotSpotMethod<TestInterpreter5$$anonfun$test1a$1.lancet$interpreter$TestInterpreter5$$anonfun$$compute$1> - HotSpotSignature<(ILlancet/interpreter/TestInterpreter5$Decompiler;)V>
      19: iload_2
      20: iconst_1
      21: iadd
      22: istore_2
      23: getstatic
      26: pop
      27: goto
      2: iload_2
      3: iload_1
      4: if_icmpge
      7: aload_0
      8: getfield
      11: iload_2
      12: aload_0
      13: getfield
      16: invokevirtual
        Call HotSpotMethod<TestInterpreter5$$anonfun$test1a$1.lancet$interpreter$TestInterpreter5$$anonfun$$compute$1> - HotSpotSignature<(ILlancet/interpreter/TestInterpreter5$Decompiler;)V>
        0: iload_1
        1: bipush
        3: if_icmpne
        10: return
        Ret HotSpotMethod<TestInterpreter5$$anonfun$test1a$1.lancet$interpreter$TestInterpreter5$$anonfun$$compute$1> - HotSpotSignature<(ILlancet/interpreter/TestInterpreter5$Decompiler;)V>
      19: iload_2
      20: iconst_1
      21: iadd
      22: istore_2
      23: getstatic
      26: pop
      27: goto
      2: iload_2
      3: iload_1
      4: if_icmpge
      7: aload_0
      8: getfield
      11: iload_2
      12: aload_0
      13: getfield
      16: invokevirtual
        Call HotSpotMethod<TestInterpreter5$$anonfun$test1a$1.lancet$interpreter$TestInterpreter5$$anonfun$$compute$1> - HotSpotSignature<(ILlancet/interpreter/TestInterpreter5$Decompiler;)V>
        0: iload_1
        1: bipush
        3: if_icmpne
        10: return
        Ret HotSpotMethod<TestInterpreter5$$anonfun$test1a$1.lancet$interpreter$TestInterpreter5$$anonfun$$compute$1> - HotSpotSignature<(ILlancet/interpreter/TestInterpreter5$Decompiler;)V>
      19: iload_2
      20: iconst_1
      21: iadd
      22: istore_2
      23: getstatic
      26: pop
      27: goto
      2: iload_2
      3: iload_1
      4: if_icmpge
      7: aload_0
      8: getfield
      11: iload_2
      12: aload_0
      13: getfield
      16: invokevirtual
        Call HotSpotMethod<TestInterpreter5$$anonfun$test1a$1.lancet$interpreter$TestInterpreter5$$anonfun$$compute$1> - HotSpotSignature<(ILlancet/interpreter/TestInterpreter5$Decompiler;)V>
        0: iload_1
        1: bipush
        3: if_icmpne
        10: return
        Ret HotSpotMethod<TestInterpreter5$$anonfun$test1a$1.lancet$interpreter$TestInterpreter5$$anonfun$$compute$1> - HotSpotSignature<(ILlancet/interpreter/TestInterpreter5$Decompiler;)V>
      19: iload_2
      20: iconst_1
      21: iadd
      22: istore_2
      23: getstatic
      26: pop
      27: goto
      2: iload_2
      3: iload_1
      4: if_icmpge
      7: aload_0
      8: getfield
      11: iload_2
      12: aload_0
      13: getfield
      16: invokevirtual
        Call HotSpotMethod<TestInterpreter5$$anonfun$test1a$1.lancet$interpreter$TestInterpreter5$$anonfun$$compute$1> - HotSpotSignature<(ILlancet/interpreter/TestInterpreter5$Decompiler;)V>
        0: iload_1
        1: bipush
        3: if_icmpne
        10: return
        Ret HotSpotMethod<TestInterpreter5$$anonfun$test1a$1.lancet$interpreter$TestInterpreter5$$anonfun$$compute$1> - HotSpotSignature<(ILlancet/interpreter/TestInterpreter5$Decompiler;)V>
      19: iload_2
      20: iconst_1
      21: iadd
      22: istore_2
      23: getstatic
      26: pop
      27: goto
      2: iload_2
      3: iload_1
      4: if_icmpge
      7: aload_0
      8: getfield
      11: iload_2
      12: aload_0
      13: getfield
      16: invokevirtual
        Call HotSpotMethod<TestInterpreter5$$anonfun$test1a$1.lancet$interpreter$TestInterpreter5$$anonfun$$compute$1> - HotSpotSignature<(ILlancet/interpreter/TestInterpreter5$Decompiler;)V>
        0: iload_1
        1: bipush
        3: if_icmpne
        10: return
        Ret HotSpotMethod<TestInterpreter5$$anonfun$test1a$1.lancet$interpreter$TestInterpreter5$$anonfun$$compute$1> - HotSpotSignature<(ILlancet/interpreter/TestInterpreter5$Decompiler;)V>
      19: iload_2
      20: iconst_1
      21: iadd
      22: istore_2
      23: getstatic
      26: pop
      27: goto
      2: iload_2
      3: iload_1
      4: if_icmpge
      7: aload_0
      8: getfield
      11: iload_2
      12: aload_0
      13: getfield
      16: invokevirtual
        Call HotSpotMethod<TestInterpreter5$$anonfun$test1a$1.lancet$interpreter$TestInterpreter5$$anonfun$$compute$1> - HotSpotSignature<(ILlancet/interpreter/TestInterpreter5$Decompiler;)V>
        0: iload_1
        1: bipush
        3: if_icmpne
        10: return
        Ret HotSpotMethod<TestInterpreter5$$anonfun$test1a$1.lancet$interpreter$TestInterpreter5$$anonfun$$compute$1> - HotSpotSignature<(ILlancet/interpreter/TestInterpreter5$Decompiler;)V>
      19: iload_2
      20: iconst_1
      21: iadd
      22: istore_2
      23: getstatic
      26: pop
      27: goto
      2: iload_2
      3: iload_1
      4: if_icmpge
      7: aload_0
      8: getfield
      11: iload_2
      12: aload_0
      13: getfield
      16: invokevirtual
        Call HotSpotMethod<TestInterpreter5$$anonfun$test1a$1.lancet$interpreter$TestInterpreter5$$anonfun$$compute$1> - HotSpotSignature<(ILlancet/interpreter/TestInterpreter5$Decompiler;)V>
        0: iload_1
        1: bipush
        3: if_icmpne
        10: return
        Ret HotSpotMethod<TestInterpreter5$$anonfun$test1a$1.lancet$interpreter$TestInterpreter5$$anonfun$$compute$1> - HotSpotSignature<(ILlancet/interpreter/TestInterpreter5$Decompiler;)V>
      19: iload_2
      20: iconst_1
      21: iadd
      22: istore_2
      23: getstatic
      26: pop
      27: goto
      2: iload_2
      3: iload_1
      4: if_icmpge
      7: aload_0
      8: getfield
      11: iload_2
      12: aload_0
      13: getfield
      16: invokevirtual
        Call HotSpotMethod<TestInterpreter5$$anonfun$test1a$1.lancet$interpreter$TestInterpreter5$$anonfun$$compute$1> - HotSpotSignature<(ILlancet/interpreter/TestInterpreter5$Decompiler;)V>
        0: iload_1
        1: bipush
        3: if_icmpne
        10: return
        Ret HotSpotMethod<TestInterpreter5$$anonfun$test1a$1.lancet$interpreter$TestInterpreter5$$anonfun$$compute$1> - HotSpotSignature<(ILlancet/interpreter/TestInterpreter5$Decompiler;)V>
      19: iload_2
      20: iconst_1
      21: iadd
      22: istore_2
      23: getstatic
      26: pop
      27: goto
      2: iload_2
      3: iload_1
      4: if_icmpge
      7: aload_0
      8: getfield
      11: iload_2
      12: aload_0
      13: getfield
      16: invokevirtual
        Call HotSpotMethod<TestInterpreter5$$anonfun$test1a$1.lancet$interpreter$TestInterpreter5$$anonfun$$compute$1> - HotSpotSignature<(ILlancet/interpreter/TestInterpreter5$Decompiler;)V>
        0: iload_1
        1: bipush
        3: if_icmpne
        6: aload_2
        7: invokevirtual
          Call HotSpotMethod<TestInterpreter5$Decompiler.dropdead> - HotSpotSignature<()V>
          0: return
          Ret HotSpotMethod<TestInterpreter5$Decompiler.dropdead> - HotSpotSignature<()V>
        10: return
        Ret HotSpotMethod<TestInterpreter5$$anonfun$test1a$1.lancet$interpreter$TestInterpreter5$$anonfun$$compute$1> - HotSpotSignature<(ILlancet/interpreter/TestInterpreter5$Decompiler;)V>
      19: iload_2
      20: iconst_1
      21: iadd
      22: istore_2
      23: getstatic
      26: pop
      27: goto
      2: iload_2
      3: iload_1
      4: if_icmpge
      7: aload_0
      8: getfield
      11: iload_2
      12: aload_0
      13: getfield
      16: invokevirtual
        Call HotSpotMethod<TestInterpreter5$$anonfun$test1a$1.lancet$interpreter$TestInterpreter5$$anonfun$$compute$1> - HotSpotSignature<(ILlancet/interpreter/TestInterpreter5$Decompiler;)V>
        0: iload_1
        1: bipush
        3: if_icmpne
        10: return
        Ret HotSpotMethod<TestInterpreter5$$anonfun$test1a$1.lancet$interpreter$TestInterpreter5$$anonfun$$compute$1> - HotSpotSignature<(ILlancet/interpreter/TestInterpreter5$Decompiler;)V>
      19: iload_2
      20: iconst_1
      21: iadd
      22: istore_2
      23: getstatic
      26: pop
      27: goto
      2: iload_2
      3: iload_1
      4: if_icmpge
      7: aload_0
      8: getfield
      11: iload_2
      12: aload_0
      13: getfield
      16: invokevirtual
        Call HotSpotMethod<TestInterpreter5$$anonfun$test1a$1.lancet$interpreter$TestInterpreter5$$anonfun$$compute$1> - HotSpotSignature<(ILlancet/interpreter/TestInterpreter5$Decompiler;)V>
        0: iload_1
        1: bipush
        3: if_icmpne
        10: return
        Ret HotSpotMethod<TestInterpreter5$$anonfun$test1a$1.lancet$interpreter$TestInterpreter5$$anonfun$$compute$1> - HotSpotSignature<(ILlancet/interpreter/TestInterpreter5$Decompiler;)V>
      19: iload_2
      20: iconst_1
      21: iadd
      22: istore_2
      23: getstatic
      26: pop
      27: goto
      2: iload_2
      3: iload_1
      4: if_icmpge
      7: aload_0
      8: getfield
      11: iload_2
      12: aload_0
      13: getfield
      16: invokevirtual
        Call HotSpotMethod<TestInterpreter5$$anonfun$test1a$1.lancet$interpreter$TestInterpreter5$$anonfun$$compute$1> - HotSpotSignature<(ILlancet/interpreter/TestInterpreter5$Decompiler;)V>
        0: iload_1
        1: bipush
        3: if_icmpne
        10: return
        Ret HotSpotMethod<TestInterpreter5$$anonfun$test1a$1.lancet$interpreter$TestInterpreter5$$anonfun$$compute$1> - HotSpotSignature<(ILlancet/interpreter/TestInterpreter5$Decompiler;)V>
      19: iload_2
      20: iconst_1
      21: iadd
      22: istore_2
      23: getstatic
      26: pop
      27: goto
      2: iload_2
      3: iload_1
      4: if_icmpge
      7: aload_0
      8: getfield
      11: iload_2
      12: aload_0
      13: getfield
      16: invokevirtual
        Call HotSpotMethod<TestInterpreter5$$anonfun$test1a$1.lancet$interpreter$TestInterpreter5$$anonfun$$compute$1> - HotSpotSignature<(ILlancet/interpreter/TestInterpreter5$Decompiler;)V>
        0: iload_1
        1: bipush
        3: if_icmpne
        10: return
        Ret HotSpotMethod<TestInterpreter5$$anonfun$test1a$1.lancet$interpreter$TestInterpreter5$$anonfun$$compute$1> - HotSpotSignature<(ILlancet/interpreter/TestInterpreter5$Decompiler;)V>
      19: iload_2
      20: iconst_1
      21: iadd
      22: istore_2
      23: getstatic
      26: pop
      27: goto
      2: iload_2
      3: iload_1
      4: if_icmpge
      7: aload_0
      8: getfield
      11: iload_2
      12: aload_0
      13: getfield
      16: invokevirtual
        Call HotSpotMethod<TestInterpreter5$$anonfun$test1a$1.lancet$interpreter$TestInterpreter5$$anonfun$$compute$1> - HotSpotSignature<(ILlancet/interpreter/TestInterpreter5$Decompiler;)V>
        0: iload_1
        1: bipush
        3: if_icmpne
        10: return
        Ret HotSpotMethod<TestInterpreter5$$anonfun$test1a$1.lancet$interpreter$TestInterpreter5$$anonfun$$compute$1> - HotSpotSignature<(ILlancet/interpreter/TestInterpreter5$Decompiler;)V>
      19: iload_2
      20: iconst_1
      21: iadd
      22: istore_2
      23: getstatic
      26: pop
      27: goto
      2: iload_2
      3: iload_1
      4: if_icmpge
      7: aload_0
      8: getfield
      11: iload_2
      12: aload_0
      13: getfield
      16: invokevirtual
        Call HotSpotMethod<TestInterpreter5$$anonfun$test1a$1.lancet$interpreter$TestInterpreter5$$anonfun$$compute$1> - HotSpotSignature<(ILlancet/interpreter/TestInterpreter5$Decompiler;)V>
        0: iload_1
        1: bipush
        3: if_icmpne
        10: return
        Ret HotSpotMethod<TestInterpreter5$$anonfun$test1a$1.lancet$interpreter$TestInterpreter5$$anonfun$$compute$1> - HotSpotSignature<(ILlancet/interpreter/TestInterpreter5$Decompiler;)V>
      19: iload_2
      20: iconst_1
      21: iadd
      22: istore_2
      23: getstatic
      26: pop
      27: goto
      2: iload_2
      3: iload_1
      4: if_icmpge
      7: aload_0
      8: getfield
      11: iload_2
      12: aload_0
      13: getfield
      16: invokevirtual
        Call HotSpotMethod<TestInterpreter5$$anonfun$test1a$1.lancet$interpreter$TestInterpreter5$$anonfun$$compute$1> - HotSpotSignature<(ILlancet/interpreter/TestInterpreter5$Decompiler;)V>
        0: iload_1
        1: bipush
        3: if_icmpne
        10: return
        Ret HotSpotMethod<TestInterpreter5$$anonfun$test1a$1.lancet$interpreter$TestInterpreter5$$anonfun$$compute$1> - HotSpotSignature<(ILlancet/interpreter/TestInterpreter5$Decompiler;)V>
      19: iload_2
      20: iconst_1
      21: iadd
      22: istore_2
      23: getstatic
      26: pop
      27: goto
      2: iload_2
      3: iload_1
      4: if_icmpge
      7: aload_0
      8: getfield
      11: iload_2
      12: aload_0
      13: getfield
      16: invokevirtual
        Call HotSpotMethod<TestInterpreter5$$anonfun$test1a$1.lancet$interpreter$TestInterpreter5$$anonfun$$compute$1> - HotSpotSignature<(ILlancet/interpreter/TestInterpreter5$Decompiler;)V>
        0: iload_1
        1: bipush
        3: if_icmpne
        10: return
        Ret HotSpotMethod<TestInterpreter5$$anonfun$test1a$1.lancet$interpreter$TestInterpreter5$$anonfun$$compute$1> - HotSpotSignature<(ILlancet/interpreter/TestInterpreter5$Decompiler;)V>
      19: iload_2
      20: iconst_1
      21: iadd
      22: istore_2
      23: getstatic
      26: pop
      27: goto
      2: iload_2
      3: iload_1
      4: if_icmpge
      7: aload_0
      8: getfield
      11: iload_2
      12: aload_0
      13: getfield
      16: invokevirtual
        Call HotSpotMethod<TestInterpreter5$$anonfun$test1a$1.lancet$interpreter$TestInterpreter5$$anonfun$$compute$1> - HotSpotSignature<(ILlancet/interpreter/TestInterpreter5$Decompiler;)V>
        0: iload_1
        1: bipush
        3: if_icmpne
        10: return
        Ret HotSpotMethod<TestInterpreter5$$anonfun$test1a$1.lancet$interpreter$TestInterpreter5$$anonfun$$compute$1> - HotSpotSignature<(ILlancet/interpreter/TestInterpreter5$Decompiler;)V>
      19: iload_2
      20: iconst_1
      21: iadd
      22: istore_2
      23: getstatic
      26: pop
      27: goto
      2: iload_2
      3: iload_1
      4: if_icmpge
      7: aload_0
      8: getfield
      11: iload_2
      12: aload_0
      13: getfield
      16: invokevirtual
        Call HotSpotMethod<TestInterpreter5$$anonfun$test1a$1.lancet$interpreter$TestInterpreter5$$anonfun$$compute$1> - HotSpotSignature<(ILlancet/interpreter/TestInterpreter5$Decompiler;)V>
        0: iload_1
        1: bipush
        3: if_icmpne
        10: return
        Ret HotSpotMethod<TestInterpreter5$$anonfun$test1a$1.lancet$interpreter$TestInterpreter5$$anonfun$$compute$1> - HotSpotSignature<(ILlancet/interpreter/TestInterpreter5$Decompiler;)V>
      19: iload_2
      20: iconst_1
      21: iadd
      22: istore_2
      23: getstatic
      26: pop
      27: goto
      2: iload_2
      3: iload_1
      4: if_icmpge
      7: aload_0
      8: getfield
      11: iload_2
      12: aload_0
      13: getfield
      16: invokevirtual
        Call HotSpotMethod<TestInterpreter5$$anonfun$test1a$1.lancet$interpreter$TestInterpreter5$$anonfun$$compute$1> - HotSpotSignature<(ILlancet/interpreter/TestInterpreter5$Decompiler;)V>
        0: iload_1
        1: bipush
        3: if_icmpne
        10: return
        Ret HotSpotMethod<TestInterpreter5$$anonfun$test1a$1.lancet$interpreter$TestInterpreter5$$anonfun$$compute$1> - HotSpotSignature<(ILlancet/interpreter/TestInterpreter5$Decompiler;)V>
      19: iload_2
      20: iconst_1
      21: iadd
      22: istore_2
      23: getstatic
      26: pop
      27: goto
      2: iload_2
      3: iload_1
      4: if_icmpge
      7: aload_0
      8: getfield
      11: iload_2
      12: aload_0
      13: getfield
      16: invokevirtual
        Call HotSpotMethod<TestInterpreter5$$anonfun$test1a$1.lancet$interpreter$TestInterpreter5$$anonfun$$compute$1> - HotSpotSignature<(ILlancet/interpreter/TestInterpreter5$Decompiler;)V>
        0: iload_1
        1: bipush
        3: if_icmpne
        10: return
        Ret HotSpotMethod<TestInterpreter5$$anonfun$test1a$1.lancet$interpreter$TestInterpreter5$$anonfun$$compute$1> - HotSpotSignature<(ILlancet/interpreter/TestInterpreter5$Decompiler;)V>
      19: iload_2
      20: iconst_1
      21: iadd
      22: istore_2
      23: getstatic
      26: pop
      27: goto
      2: iload_2
      3: iload_1
      4: if_icmpge
      7: aload_0
      8: getfield
      11: iload_2
      12: aload_0
      13: getfield
      16: invokevirtual
        Call HotSpotMethod<TestInterpreter5$$anonfun$test1a$1.lancet$interpreter$TestInterpreter5$$anonfun$$compute$1> - HotSpotSignature<(ILlancet/interpreter/TestInterpreter5$Decompiler;)V>
        0: iload_1
        1: bipush
        3: if_icmpne
        10: return
        Ret HotSpotMethod<TestInterpreter5$$anonfun$test1a$1.lancet$interpreter$TestInterpreter5$$anonfun$$compute$1> - HotSpotSignature<(ILlancet/interpreter/TestInterpreter5$Decompiler;)V>
      19: iload_2
      20: iconst_1
      21: iadd
      22: istore_2
      23: getstatic
      26: pop
      27: goto
      2: iload_2
      3: iload_1
      4: if_icmpge
      7: aload_0
      8: getfield
      11: iload_2
      12: aload_0
      13: getfield
      16: invokevirtual
        Call HotSpotMethod<TestInterpreter5$$anonfun$test1a$1.lancet$interpreter$TestInterpreter5$$anonfun$$compute$1> - HotSpotSignature<(ILlancet/interpreter/TestInterpreter5$Decompiler;)V>
        0: iload_1
        1: bipush
        3: if_icmpne
        10: return
        Ret HotSpotMethod<TestInterpreter5$$anonfun$test1a$1.lancet$interpreter$TestInterpreter5$$anonfun$$compute$1> - HotSpotSignature<(ILlancet/interpreter/TestInterpreter5$Decompiler;)V>
      19: iload_2
      20: iconst_1
      21: iadd
      22: istore_2
      23: getstatic
      26: pop
      27: goto
      2: iload_2
      3: iload_1
      4: if_icmpge
      7: aload_0
      8: getfield
      11: iload_2
      12: aload_0
      13: getfield
      16: invokevirtual
        Call HotSpotMethod<TestInterpreter5$$anonfun$test1a$1.lancet$interpreter$TestInterpreter5$$anonfun$$compute$1> - HotSpotSignature<(ILlancet/interpreter/TestInterpreter5$Decompiler;)V>
        0: iload_1
        1: bipush
        3: if_icmpne
        10: return
        Ret HotSpotMethod<TestInterpreter5$$anonfun$test1a$1.lancet$interpreter$TestInterpreter5$$anonfun$$compute$1> - HotSpotSignature<(ILlancet/interpreter/TestInterpreter5$Decompiler;)V>
      19: iload_2
      20: iconst_1
      21: iadd
      22: istore_2
      23: getstatic
      26: pop
      27: goto
      2: iload_2
      3: iload_1
      4: if_icmpge
      7: aload_0
      8: getfield
      11: iload_2
      12: aload_0
      13: getfield
      16: invokevirtual
        Call HotSpotMethod<TestInterpreter5$$anonfun$test1a$1.lancet$interpreter$TestInterpreter5$$anonfun$$compute$1> - HotSpotSignature<(ILlancet/interpreter/TestInterpreter5$Decompiler;)V>
        0: iload_1
        1: bipush
        3: if_icmpne
        10: return
        Ret HotSpotMethod<TestInterpreter5$$anonfun$test1a$1.lancet$interpreter$TestInterpreter5$$anonfun$$compute$1> - HotSpotSignature<(ILlancet/interpreter/TestInterpreter5$Decompiler;)V>
      19: iload_2
      20: iconst_1
      21: iadd
      22: istore_2
      23: getstatic
      26: pop
      27: goto
      2: iload_2
      3: iload_1
      4: if_icmpge
      7: aload_0
      8: getfield
      11: iload_2
      12: aload_0
      13: getfield
      16: invokevirtual
        Call HotSpotMethod<TestInterpreter5$$anonfun$test1a$1.lancet$interpreter$TestInterpreter5$$anonfun$$compute$1> - HotSpotSignature<(ILlancet/interpreter/TestInterpreter5$Decompiler;)V>
        0: iload_1
        1: bipush
        3: if_icmpne
        10: return
        Ret HotSpotMethod<TestInterpreter5$$anonfun$test1a$1.lancet$interpreter$TestInterpreter5$$anonfun$$compute$1> - HotSpotSignature<(ILlancet/interpreter/TestInterpreter5$Decompiler;)V>
      19: iload_2
      20: iconst_1
      21: iadd
      22: istore_2
      23: getstatic
      26: pop
      27: goto
      2: iload_2
      3: iload_1
      4: if_icmpge
      7: aload_0
      8: getfield
      11: iload_2
      12: aload_0
      13: getfield
      16: invokevirtual
        Call HotSpotMethod<TestInterpreter5$$anonfun$test1a$1.lancet$interpreter$TestInterpreter5$$anonfun$$compute$1> - HotSpotSignature<(ILlancet/interpreter/TestInterpreter5$Decompiler;)V>
        0: iload_1
        1: bipush
        3: if_icmpne
        10: return
        Ret HotSpotMethod<TestInterpreter5$$anonfun$test1a$1.lancet$interpreter$TestInterpreter5$$anonfun$$compute$1> - HotSpotSignature<(ILlancet/interpreter/TestInterpreter5$Decompiler;)V>
      19: iload_2
      20: iconst_1
      21: iadd
      22: istore_2
      23: getstatic
      26: pop
      27: goto
      2: iload_2
      3: iload_1
      4: if_icmpge
      7: aload_0
      8: getfield
      11: iload_2
      12: aload_0
      13: getfield
      16: invokevirtual
        Call HotSpotMethod<TestInterpreter5$$anonfun$test1a$1.lancet$interpreter$TestInterpreter5$$anonfun$$compute$1> - HotSpotSignature<(ILlancet/interpreter/TestInterpreter5$Decompiler;)V>
        0: iload_1
        1: bipush
        3: if_icmpne
        10: return
        Ret HotSpotMethod<TestInterpreter5$$anonfun$test1a$1.lancet$interpreter$TestInterpreter5$$anonfun$$compute$1> - HotSpotSignature<(ILlancet/interpreter/TestInterpreter5$Decompiler;)V>
      19: iload_2
      20: iconst_1
      21: iadd
      22: istore_2
      23: getstatic
      26: pop
      27: goto
      2: iload_2
      3: iload_1
      4: if_icmpge
      7: aload_0
      8: getfield
      11: iload_2
      12: aload_0
      13: getfield
      16: invokevirtual
        Call HotSpotMethod<TestInterpreter5$$anonfun$test1a$1.lancet$interpreter$TestInterpreter5$$anonfun$$compute$1> - HotSpotSignature<(ILlancet/interpreter/TestInterpreter5$Decompiler;)V>
        0: iload_1
        1: bipush
        3: if_icmpne
        10: return
        Ret HotSpotMethod<TestInterpreter5$$anonfun$test1a$1.lancet$interpreter$TestInterpreter5$$anonfun$$compute$1> - HotSpotSignature<(ILlancet/interpreter/TestInterpreter5$Decompiler;)V>
      19: iload_2
      20: iconst_1
      21: iadd
      22: istore_2
      23: getstatic
      26: pop
      27: goto
      2: iload_2
      3: iload_1
      4: if_icmpge
      7: aload_0
      8: getfield
      11: iload_2
      12: aload_0
      13: getfield
      16: invokevirtual
        Call HotSpotMethod<TestInterpreter5$$anonfun$test1a$1.lancet$interpreter$TestInterpreter5$$anonfun$$compute$1> - HotSpotSignature<(ILlancet/interpreter/TestInterpreter5$Decompiler;)V>
        0: iload_1
        1: bipush
        3: if_icmpne
        10: return
        Ret HotSpotMethod<TestInterpreter5$$anonfun$test1a$1.lancet$interpreter$TestInterpreter5$$anonfun$$compute$1> - HotSpotSignature<(ILlancet/interpreter/TestInterpreter5$Decompiler;)V>
      19: iload_2
      20: iconst_1
      21: iadd
      22: istore_2
      23: getstatic
      26: pop
      27: goto
      2: iload_2
      3: iload_1
      4: if_icmpge
      7: aload_0
      8: getfield
      11: iload_2
      12: aload_0
      13: getfield
      16: invokevirtual
        Call HotSpotMethod<TestInterpreter5$$anonfun$test1a$1.lancet$interpreter$TestInterpreter5$$anonfun$$compute$1> - HotSpotSignature<(ILlancet/interpreter/TestInterpreter5$Decompiler;)V>
        0: iload_1
        1: bipush
        3: if_icmpne
        10: return
        Ret HotSpotMethod<TestInterpreter5$$anonfun$test1a$1.lancet$interpreter$TestInterpreter5$$anonfun$$compute$1> - HotSpotSignature<(ILlancet/interpreter/TestInterpreter5$Decompiler;)V>
      19: iload_2
      20: iconst_1
      21: iadd
      22: istore_2
      23: getstatic
      26: pop
      27: goto
      2: iload_2
      3: iload_1
      4: if_icmpge
      7: aload_0
      8: getfield
      11: iload_2
      12: aload_0
      13: getfield
      16: invokevirtual
        Call HotSpotMethod<TestInterpreter5$$anonfun$test1a$1.lancet$interpreter$TestInterpreter5$$anonfun$$compute$1> - HotSpotSignature<(ILlancet/interpreter/TestInterpreter5$Decompiler;)V>
        0: iload_1
        1: bipush
        3: if_icmpne
        10: return
        Ret HotSpotMethod<TestInterpreter5$$anonfun$test1a$1.lancet$interpreter$TestInterpreter5$$anonfun$$compute$1> - HotSpotSignature<(ILlancet/interpreter/TestInterpreter5$Decompiler;)V>
      19: iload_2
      20: iconst_1
      21: iadd
      22: istore_2
      23: getstatic
      26: pop
      27: goto
      2: iload_2
      3: iload_1
      4: if_icmpge
      7: aload_0
      8: getfield
      11: iload_2
      12: aload_0
      13: getfield
      16: invokevirtual
        Call HotSpotMethod<TestInterpreter5$$anonfun$test1a$1.lancet$interpreter$TestInterpreter5$$anonfun$$compute$1> - HotSpotSignature<(ILlancet/interpreter/TestInterpreter5$Decompiler;)V>
        0: iload_1
        1: bipush
        3: if_icmpne
        10: return
        Ret HotSpotMethod<TestInterpreter5$$anonfun$test1a$1.lancet$interpreter$TestInterpreter5$$anonfun$$compute$1> - HotSpotSignature<(ILlancet/interpreter/TestInterpreter5$Decompiler;)V>
      19: iload_2
      20: iconst_1
      21: iadd
      22: istore_2
      23: getstatic
      26: pop
      27: goto
      2: iload_2
      3: iload_1
      4: if_icmpge
      7: aload_0
      8: getfield
      11: iload_2
      12: aload_0
      13: getfield
      16: invokevirtual
        Call HotSpotMethod<TestInterpreter5$$anonfun$test1a$1.lancet$interpreter$TestInterpreter5$$anonfun$$compute$1> - HotSpotSignature<(ILlancet/interpreter/TestInterpreter5$Decompiler;)V>
        0: iload_1
        1: bipush
        3: if_icmpne
        10: return
        Ret HotSpotMethod<TestInterpreter5$$anonfun$test1a$1.lancet$interpreter$TestInterpreter5$$anonfun$$compute$1> - HotSpotSignature<(ILlancet/interpreter/TestInterpreter5$Decompiler;)V>
      19: iload_2
      20: iconst_1
      21: iadd
      22: istore_2
      23: getstatic
      26: pop
      27: goto
      2: iload_2
      3: iload_1
      4: if_icmpge
      7: aload_0
      8: getfield
      11: iload_2
      12: aload_0
      13: getfield
      16: invokevirtual
        Call HotSpotMethod<TestInterpreter5$$anonfun$test1a$1.lancet$interpreter$TestInterpreter5$$anonfun$$compute$1> - HotSpotSignature<(ILlancet/interpreter/TestInterpreter5$Decompiler;)V>
        0: iload_1
        1: bipush
        3: if_icmpne
        10: return
        Ret HotSpotMethod<TestInterpreter5$$anonfun$test1a$1.lancet$interpreter$TestInterpreter5$$anonfun$$compute$1> - HotSpotSignature<(ILlancet/interpreter/TestInterpreter5$Decompiler;)V>
      19: iload_2
      20: iconst_1
      21: iadd
      22: istore_2
      23: getstatic
      26: pop
      27: goto
      2: iload_2
      3: iload_1
      4: if_icmpge
      7: aload_0
      8: getfield
      11: iload_2
      12: aload_0
      13: getfield
      16: invokevirtual
        Call HotSpotMethod<TestInterpreter5$$anonfun$test1a$1.lancet$interpreter$TestInterpreter5$$anonfun$$compute$1> - HotSpotSignature<(ILlancet/interpreter/TestInterpreter5$Decompiler;)V>
        0: iload_1
        1: bipush
        3: if_icmpne
        10: return
        Ret HotSpotMethod<TestInterpreter5$$anonfun$test1a$1.lancet$interpreter$TestInterpreter5$$anonfun$$compute$1> - HotSpotSignature<(ILlancet/interpreter/TestInterpreter5$Decompiler;)V>
      19: iload_2
      20: iconst_1
      21: iadd
      22: istore_2
      23: getstatic
      26: pop
      27: goto
      2: iload_2
      3: iload_1
      4: if_icmpge
      7: aload_0
      8: getfield
      11: iload_2
      12: aload_0
      13: getfield
      16: invokevirtual
        Call HotSpotMethod<TestInterpreter5$$anonfun$test1a$1.lancet$interpreter$TestInterpreter5$$anonfun$$compute$1> - HotSpotSignature<(ILlancet/interpreter/TestInterpreter5$Decompiler;)V>
        0: iload_1
        1: bipush
        3: if_icmpne
        10: return
        Ret HotSpotMethod<TestInterpreter5$$anonfun$test1a$1.lancet$interpreter$TestInterpreter5$$anonfun$$compute$1> - HotSpotSignature<(ILlancet/interpreter/TestInterpreter5$Decompiler;)V>
      19: iload_2
      20: iconst_1
      21: iadd
      22: istore_2
      23: getstatic
      26: pop
      27: goto
      2: iload_2
      3: iload_1
      4: if_icmpge
      7: aload_0
      8: getfield
      11: iload_2
      12: aload_0
      13: getfield
      16: invokevirtual
        Call HotSpotMethod<TestInterpreter5$$anonfun$test1a$1.lancet$interpreter$TestInterpreter5$$anonfun$$compute$1> - HotSpotSignature<(ILlancet/interpreter/TestInterpreter5$Decompiler;)V>
        0: iload_1
        1: bipush
        3: if_icmpne
        10: return
        Ret HotSpotMethod<TestInterpreter5$$anonfun$test1a$1.lancet$interpreter$TestInterpreter5$$anonfun$$compute$1> - HotSpotSignature<(ILlancet/interpreter/TestInterpreter5$Decompiler;)V>
      19: iload_2
      20: iconst_1
      21: iadd
      22: istore_2
      23: getstatic
      26: pop
      27: goto
      2: iload_2
      3: iload_1
      4: if_icmpge
      7: aload_0
      8: getfield
      11: iload_2
      12: aload_0
      13: getfield
      16: invokevirtual
        Call HotSpotMethod<TestInterpreter5$$anonfun$test1a$1.lancet$interpreter$TestInterpreter5$$anonfun$$compute$1> - HotSpotSignature<(ILlancet/interpreter/TestInterpreter5$Decompiler;)V>
        0: iload_1
        1: bipush
        3: if_icmpne
        10: return
        Ret HotSpotMethod<TestInterpreter5$$anonfun$test1a$1.lancet$interpreter$TestInterpreter5$$anonfun$$compute$1> - HotSpotSignature<(ILlancet/interpreter/TestInterpreter5$Decompiler;)V>
      19: iload_2
      20: iconst_1
      21: iadd
      22: istore_2
      23: getstatic
      26: pop
      27: goto
      2: iload_2
      3: iload_1
      4: if_icmpge
      7: aload_0
      8: getfield
      11: iload_2
      12: aload_0
      13: getfield
      16: invokevirtual
        Call HotSpotMethod<TestInterpreter5$$anonfun$test1a$1.lancet$interpreter$TestInterpreter5$$anonfun$$compute$1> - HotSpotSignature<(ILlancet/interpreter/TestInterpreter5$Decompiler;)V>
        0: iload_1
        1: bipush
        3: if_icmpne
        10: return
        Ret HotSpotMethod<TestInterpreter5$$anonfun$test1a$1.lancet$interpreter$TestInterpreter5$$anonfun$$compute$1> - HotSpotSignature<(ILlancet/interpreter/TestInterpreter5$Decompiler;)V>
      19: iload_2
      20: iconst_1
      21: iadd
      22: istore_2
      23: getstatic
      26: pop
      27: goto
      2: iload_2
      3: iload_1
      4: if_icmpge
      7: aload_0
      8: getfield
      11: iload_2
      12: aload_0
      13: getfield
      16: invokevirtual
        Call HotSpotMethod<TestInterpreter5$$anonfun$test1a$1.lancet$interpreter$TestInterpreter5$$anonfun$$compute$1> - HotSpotSignature<(ILlancet/interpreter/TestInterpreter5$Decompiler;)V>
        0: iload_1
        1: bipush
        3: if_icmpne
        10: return
        Ret HotSpotMethod<TestInterpreter5$$anonfun$test1a$1.lancet$interpreter$TestInterpreter5$$anonfun$$compute$1> - HotSpotSignature<(ILlancet/interpreter/TestInterpreter5$Decompiler;)V>
      19: iload_2
      20: iconst_1
      21: iadd
      22: istore_2
      23: getstatic
      26: pop
      27: goto
      2: iload_2
      3: iload_1
      4: if_icmpge
      7: aload_0
      8: getfield
      11: iload_2
      12: aload_0
      13: getfield
      16: invokevirtual
        Call HotSpotMethod<TestInterpreter5$$anonfun$test1a$1.lancet$interpreter$TestInterpreter5$$anonfun$$compute$1> - HotSpotSignature<(ILlancet/interpreter/TestInterpreter5$Decompiler;)V>
        0: iload_1
        1: bipush
        3: if_icmpne
        10: return
        Ret HotSpotMethod<TestInterpreter5$$anonfun$test1a$1.lancet$interpreter$TestInterpreter5$$anonfun$$compute$1> - HotSpotSignature<(ILlancet/interpreter/TestInterpreter5$Decompiler;)V>
      19: iload_2
      20: iconst_1
      21: iadd
      22: istore_2
      23: getstatic
      26: pop
      27: goto
      2: iload_2
      3: iload_1
      4: if_icmpge
      7: aload_0
      8: getfield
      11: iload_2
      12: aload_0
      13: getfield
      16: invokevirtual
        Call HotSpotMethod<TestInterpreter5$$anonfun$test1a$1.lancet$interpreter$TestInterpreter5$$anonfun$$compute$1> - HotSpotSignature<(ILlancet/interpreter/TestInterpreter5$Decompiler;)V>
        0: iload_1
        1: bipush
        3: if_icmpne
        10: return
        Ret HotSpotMethod<TestInterpreter5$$anonfun$test1a$1.lancet$interpreter$TestInterpreter5$$anonfun$$compute$1> - HotSpotSignature<(ILlancet/interpreter/TestInterpreter5$Decompiler;)V>
      19: iload_2
      20: iconst_1
      21: iadd
      22: istore_2
      23: getstatic
      26: pop
      27: goto
      2: iload_2
      3: iload_1
      4: if_icmpge
      7: aload_0
      8: getfield
      11: iload_2
      12: aload_0
      13: getfield
      16: invokevirtual
        Call HotSpotMethod<TestInterpreter5$$anonfun$test1a$1.lancet$interpreter$TestInterpreter5$$anonfun$$compute$1> - HotSpotSignature<(ILlancet/interpreter/TestInterpreter5$Decompiler;)V>
        0: iload_1
        1: bipush
        3: if_icmpne
        10: return
        Ret HotSpotMethod<TestInterpreter5$$anonfun$test1a$1.lancet$interpreter$TestInterpreter5$$anonfun$$compute$1> - HotSpotSignature<(ILlancet/interpreter/TestInterpreter5$Decompiler;)V>
      19: iload_2
      20: iconst_1
      21: iadd
      22: istore_2
      23: getstatic
      26: pop
      27: goto
      2: iload_2
      3: iload_1
      4: if_icmpge
      7: aload_0
      8: getfield
      11: iload_2
      12: aload_0
      13: getfield
      16: invokevirtual
        Call HotSpotMethod<TestInterpreter5$$anonfun$test1a$1.lancet$interpreter$TestInterpreter5$$anonfun$$compute$1> - HotSpotSignature<(ILlancet/interpreter/TestInterpreter5$Decompiler;)V>
        0: iload_1
        1: bipush
        3: if_icmpne
        10: return
        Ret HotSpotMethod<TestInterpreter5$$anonfun$test1a$1.lancet$interpreter$TestInterpreter5$$anonfun$$compute$1> - HotSpotSignature<(ILlancet/interpreter/TestInterpreter5$Decompiler;)V>
      19: iload_2
      20: iconst_1
      21: iadd
      22: istore_2
      23: getstatic
      26: pop
      27: goto
      2: iload_2
      3: iload_1
      4: if_icmpge
      7: aload_0
      8: getfield
      11: iload_2
      12: aload_0
      13: getfield
      16: invokevirtual
        Call HotSpotMethod<TestInterpreter5$$anonfun$test1a$1.lancet$interpreter$TestInterpreter5$$anonfun$$compute$1> - HotSpotSignature<(ILlancet/interpreter/TestInterpreter5$Decompiler;)V>
        0: iload_1
        1: bipush
        3: if_icmpne
        10: return
        Ret HotSpotMethod<TestInterpreter5$$anonfun$test1a$1.lancet$interpreter$TestInterpreter5$$anonfun$$compute$1> - HotSpotSignature<(ILlancet/interpreter/TestInterpreter5$Decompiler;)V>
      19: iload_2
      20: iconst_1
      21: iadd
      22: istore_2
      23: getstatic
      26: pop
      27: goto
      2: iload_2
      3: iload_1
      4: if_icmpge
      7: aload_0
      8: getfield
      11: iload_2
      12: aload_0
      13: getfield
      16: invokevirtual
        Call HotSpotMethod<TestInterpreter5$$anonfun$test1a$1.lancet$interpreter$TestInterpreter5$$anonfun$$compute$1> - HotSpotSignature<(ILlancet/interpreter/TestInterpreter5$Decompiler;)V>
        0: iload_1
        1: bipush
        3: if_icmpne
        10: return
        Ret HotSpotMethod<TestInterpreter5$$anonfun$test1a$1.lancet$interpreter$TestInterpreter5$$anonfun$$compute$1> - HotSpotSignature<(ILlancet/interpreter/TestInterpreter5$Decompiler;)V>
      19: iload_2
      20: iconst_1
      21: iadd
      22: istore_2
      23: getstatic
      26: pop
      27: goto
      2: iload_2
      3: iload_1
      4: if_icmpge
      7: aload_0
      8: getfield
      11: iload_2
      12: aload_0
      13: getfield
      16: invokevirtual
        Call HotSpotMethod<TestInterpreter5$$anonfun$test1a$1.lancet$interpreter$TestInterpreter5$$anonfun$$compute$1> - HotSpotSignature<(ILlancet/interpreter/TestInterpreter5$Decompiler;)V>
        0: iload_1
        1: bipush
        3: if_icmpne
        10: return
        Ret HotSpotMethod<TestInterpreter5$$anonfun$test1a$1.lancet$interpreter$TestInterpreter5$$anonfun$$compute$1> - HotSpotSignature<(ILlancet/interpreter/TestInterpreter5$Decompiler;)V>
      19: iload_2
      20: iconst_1
      21: iadd
      22: istore_2
      23: getstatic
      26: pop
      27: goto
      2: iload_2
      3: iload_1
      4: if_icmpge
      7: aload_0
      8: getfield
      11: iload_2
      12: aload_0
      13: getfield
      16: invokevirtual
        Call HotSpotMethod<TestInterpreter5$$anonfun$test1a$1.lancet$interpreter$TestInterpreter5$$anonfun$$compute$1> - HotSpotSignature<(ILlancet/interpreter/TestInterpreter5$Decompiler;)V>
        0: iload_1
        1: bipush
        3: if_icmpne
        10: return
        Ret HotSpotMethod<TestInterpreter5$$anonfun$test1a$1.lancet$interpreter$TestInterpreter5$$anonfun$$compute$1> - HotSpotSignature<(ILlancet/interpreter/TestInterpreter5$Decompiler;)V>
      19: iload_2
      20: iconst_1
      21: iadd
      22: istore_2
      23: getstatic
      26: pop
      27: goto
      2: iload_2
      3: iload_1
      4: if_icmpge
      7: aload_0
      8: getfield
      11: iload_2
      12: aload_0
      13: getfield
      16: invokevirtual
        Call HotSpotMethod<TestInterpreter5$$anonfun$test1a$1.lancet$interpreter$TestInterpreter5$$anonfun$$compute$1> - HotSpotSignature<(ILlancet/interpreter/TestInterpreter5$Decompiler;)V>
        0: iload_1
        1: bipush
        3: if_icmpne
        10: return
        Ret HotSpotMethod<TestInterpreter5$$anonfun$test1a$1.lancet$interpreter$TestInterpreter5$$anonfun$$compute$1> - HotSpotSignature<(ILlancet/interpreter/TestInterpreter5$Decompiler;)V>
      19: iload_2
      20: iconst_1
      21: iadd
      22: istore_2
      23: getstatic
      26: pop
      27: goto
      2: iload_2
      3: iload_1
      4: if_icmpge
      7: aload_0
      8: getfield
      11: iload_2
      12: aload_0
      13: getfield
      16: invokevirtual
        Call HotSpotMethod<TestInterpreter5$$anonfun$test1a$1.lancet$interpreter$TestInterpreter5$$anonfun$$compute$1> - HotSpotSignature<(ILlancet/interpreter/TestInterpreter5$Decompiler;)V>
        0: iload_1
        1: bipush
        3: if_icmpne
        10: return
        Ret HotSpotMethod<TestInterpreter5$$anonfun$test1a$1.lancet$interpreter$TestInterpreter5$$anonfun$$compute$1> - HotSpotSignature<(ILlancet/interpreter/TestInterpreter5$Decompiler;)V>
      19: iload_2
      20: iconst_1
      21: iadd
      22: istore_2
      23: getstatic
      26: pop
      27: goto
      2: iload_2
      3: iload_1
      4: if_icmpge
      7: aload_0
      8: getfield
      11: iload_2
      12: aload_0
      13: getfield
      16: invokevirtual
        Call HotSpotMethod<TestInterpreter5$$anonfun$test1a$1.lancet$interpreter$TestInterpreter5$$anonfun$$compute$1> - HotSpotSignature<(ILlancet/interpreter/TestInterpreter5$Decompiler;)V>
        0: iload_1
        1: bipush
        3: if_icmpne
        10: return
        Ret HotSpotMethod<TestInterpreter5$$anonfun$test1a$1.lancet$interpreter$TestInterpreter5$$anonfun$$compute$1> - HotSpotSignature<(ILlancet/interpreter/TestInterpreter5$Decompiler;)V>
      19: iload_2
      20: iconst_1
      21: iadd
      22: istore_2
      23: getstatic
      26: pop
      27: goto
      2: iload_2
      3: iload_1
      4: if_icmpge
      7: aload_0
      8: getfield
      11: iload_2
      12: aload_0
      13: getfield
      16: invokevirtual
        Call HotSpotMethod<TestInterpreter5$$anonfun$test1a$1.lancet$interpreter$TestInterpreter5$$anonfun$$compute$1> - HotSpotSignature<(ILlancet/interpreter/TestInterpreter5$Decompiler;)V>
        0: iload_1
        1: bipush
        3: if_icmpne
        10: return
        Ret HotSpotMethod<TestInterpreter5$$anonfun$test1a$1.lancet$interpreter$TestInterpreter5$$anonfun$$compute$1> - HotSpotSignature<(ILlancet/interpreter/TestInterpreter5$Decompiler;)V>
      19: iload_2
      20: iconst_1
      21: iadd
      22: istore_2
      23: getstatic
      26: pop
      27: goto
      2: iload_2
      3: iload_1
      4: if_icmpge
      7: aload_0
      8: getfield
      11: iload_2
      12: aload_0
      13: getfield
      16: invokevirtual
        Call HotSpotMethod<TestInterpreter5$$anonfun$test1a$1.lancet$interpreter$TestInterpreter5$$anonfun$$compute$1> - HotSpotSignature<(ILlancet/interpreter/TestInterpreter5$Decompiler;)V>
        0: iload_1
        1: bipush
        3: if_icmpne
        10: return
        Ret HotSpotMethod<TestInterpreter5$$anonfun$test1a$1.lancet$interpreter$TestInterpreter5$$anonfun$$compute$1> - HotSpotSignature<(ILlancet/interpreter/TestInterpreter5$Decompiler;)V>
      19: iload_2
      20: iconst_1
      21: iadd
      22: istore_2
      23: getstatic
      26: pop
      27: goto
      2: iload_2
      3: iload_1
      4: if_icmpge
      7: aload_0
      8: getfield
      11: iload_2
      12: aload_0
      13: getfield
      16: invokevirtual
        Call HotSpotMethod<TestInterpreter5$$anonfun$test1a$1.lancet$interpreter$TestInterpreter5$$anonfun$$compute$1> - HotSpotSignature<(ILlancet/interpreter/TestInterpreter5$Decompiler;)V>
        0: iload_1
        1: bipush
        3: if_icmpne
        10: return
        Ret HotSpotMethod<TestInterpreter5$$anonfun$test1a$1.lancet$interpreter$TestInterpreter5$$anonfun$$compute$1> - HotSpotSignature<(ILlancet/interpreter/TestInterpreter5$Decompiler;)V>
      19: iload_2
      20: iconst_1
      21: iadd
      22: istore_2
      23: getstatic
      26: pop
      27: goto
      2: iload_2
      3: iload_1
      4: if_icmpge
      7: aload_0
      8: getfield
      11: iload_2
      12: aload_0
      13: getfield
      16: invokevirtual
        Call HotSpotMethod<TestInterpreter5$$anonfun$test1a$1.lancet$interpreter$TestInterpreter5$$anonfun$$compute$1> - HotSpotSignature<(ILlancet/interpreter/TestInterpreter5$Decompiler;)V>
        0: iload_1
        1: bipush
        3: if_icmpne
        10: return
        Ret HotSpotMethod<TestInterpreter5$$anonfun$test1a$1.lancet$interpreter$TestInterpreter5$$anonfun$$compute$1> - HotSpotSignature<(ILlancet/interpreter/TestInterpreter5$Decompiler;)V>
      19: iload_2
      20: iconst_1
      21: iadd
      22: istore_2
      23: getstatic
      26: pop
      27: goto
      2: iload_2
      3: iload_1
      4: if_icmpge
      7: aload_0
      8: getfield
      11: iload_2
      12: aload_0
      13: getfield
      16: invokevirtual
        Call HotSpotMethod<TestInterpreter5$$anonfun$test1a$1.lancet$interpreter$TestInterpreter5$$anonfun$$compute$1> - HotSpotSignature<(ILlancet/interpreter/TestInterpreter5$Decompiler;)V>
        0: iload_1
        1: bipush
        3: if_icmpne
        10: return
        Ret HotSpotMethod<TestInterpreter5$$anonfun$test1a$1.lancet$interpreter$TestInterpreter5$$anonfun$$compute$1> - HotSpotSignature<(ILlancet/interpreter/TestInterpreter5$Decompiler;)V>
      19: iload_2
      20: iconst_1
      21: iadd
      22: istore_2
      23: getstatic
      26: pop
      27: goto
      2: iload_2
      3: iload_1
      4: if_icmpge
      7: aload_0
      8: getfield
      11: iload_2
      12: aload_0
      13: getfield
      16: invokevirtual
        Call HotSpotMethod<TestInterpreter5$$anonfun$test1a$1.lancet$interpreter$TestInterpreter5$$anonfun$$compute$1> - HotSpotSignature<(ILlancet/interpreter/TestInterpreter5$Decompiler;)V>
        0: iload_1
        1: bipush
        3: if_icmpne
        10: return
        Ret HotSpotMethod<TestInterpreter5$$anonfun$test1a$1.lancet$interpreter$TestInterpreter5$$anonfun$$compute$1> - HotSpotSignature<(ILlancet/interpreter/TestInterpreter5$Decompiler;)V>
      19: iload_2
      20: iconst_1
      21: iadd
      22: istore_2
      23: getstatic
      26: pop
      27: goto
      2: iload_2
      3: iload_1
      4: if_icmpge
      30: iload_2
      31: ireturn
      Ret HotSpotMethod<TestInterpreter5$$anonfun$test1a$1$$anonfun$1.apply$mcII$sp> - HotSpotSignature<(I)I>
    5: ireturn
    Ret HotSpotMethod<TestInterpreter5$$anonfun$test1a$1$$anonfun$1.apply> - HotSpotSignature<(I)I>
100
